Workbook
Name CAJA_DE_CAPTACION: #REF!
Name LIN_DISTR_ELECT.: '[1]PRES 1'!#REF!
Name SUBEST_ELECTR: '[1]PRES 1'!#REF!

Sheet DATOS
C1: ESTUDIO FINANCIERO
C3: DATOS ADICIONALES
C5: Inflación | D5: 0.09 | E5: Anual
C6: Incremento salarial | D6: 0.12 | E6: Anual
C7: Incremento volumen | D7: 0.03 | E7: cada 3 meses durante el primer año
C8: Incremento precio unitario de venta | D8: 0.09 | E8: A partir del segundo semestre del primer año y durante los sig años
C10: Depreciación en línea recta | E10: LISR
C12: Amortización de la deuda de acuerdo a la
C13: dependencia que otorgará el financiamiento
C17: Se siembra en ambos terrenos a la vez

Sheet ESTRUCTURA FINANCIERA
A1: ESTUDIO FINANCIERO
A3: ESTRUCTURA FINANCIERA
A5: PROYECTO: | B5: Implementación de semilla CP57-536
A6: SOCIEDAD | B6: Caña de la Loma
A7: BENEFICIARIOS:
A9: DESGLOSE DE INVERSION PARA UN AÑO
A10: CONCEPTO | B10: UNIDAD DE | C10: CANTIDAD | D10: PRECIO | E10: COSTO | F10: APORTACION | J10: CONCEPTO | K10: UNIDAD DE MEDIDA | L10: CANTIDAD | M10: PRECIO UNITARIO | N10: COSTO TOTAL
B11: MEDIDA | D11: UNITARIO | E11: TOTAL | F11: DEPENDENCIA | G11: GRUPO
A12: CAPITAL DE TRABAJO | F12: FIRA 80% | G12: Caña de la Loma 20% | J12: Semilla | K12: Toneladas | L12: 38.1 | M12: 1100 | N12: =L12*M12 -> 41910
A13: Semilla | B13: Toneladas | C13: 38.1 | D13: 1100 | E13: =C13*D13 -> 41910 | F13: =E13*0.8 -> 33528 | G13: =E13*0.2 -> 8382
A14: Enraizadores | B14: Costales | C14: 22.86 | D14: 1300 | E14: =C14*D14 -> 29718 | F14: =E14*0.8 -> 23774.4 | G14: =E14*0.2 -> 5943.6
A15: Aplicación de enraizadores | B15: Hectáreas | C15: 3.81 | D15: 300 | E15: =C15*D15 -> 1143 | F15: =E15*0.8 -> 914.4 | G15: =E15*0.2 -> 228.6
A16: Herbicidas | B16: Litros | C16: 30.48 | D16: 120 | E16: =C16*D16*3 -> 10972.8 | F16: =E16*0.8 -> 8778.24 | G16: =E16*0.2 -> 2194.56
A17: Aplicación de herbicidas | B17: Hectáreas | C17: 3.81 | D17: 300 | E17: =C17*D17*3 -> 3429 | F17: =E17*0.8 -> 2743.2 | G17: =E17*0.2 -> 685.8
A18: Insecticidas | B18: Litros | C18: 3.81 | D18: 115 | E18: =C18*D18*4 -> 1752.6 | F18: =E18*0.8 -> 1402.08 | G18: =E18*0.2 -> 350.52
A19: Aplicación de insecticidas | B19: Hectáreas | C19: 3.81 | D19: 300 | E19: =C19*D19*4 -> 4572 | F19: =E19*0.8 -> 3657.6 | G19: =E19*0.2 -> 914.4
A20: Fungicidas | B20: Kilos | C20: =4*3.81 -> 15.24 | D20: 92.5 | E20: =C20*D20 -> 1409.7 | F20: =E20*0.8 -> 1127.76 | G20: =E20*0.2 -> 281.94
A21: Aplicación de fungicidas | B21: Hectáreas | C21: 3.81 | D21: 300 | E21: =C21*D21*4 -> 4572 | F21: =E21*0.8 -> 3657.6 | G21: =E21*0.2 -> 914.4
A22: Coadyuvantes | B22: Litros | C22: 3.81 | D22: 72 | E22: =C22*D22*4 -> 1097.28 | F22: =E22*0.8 -> 877.824 | G22: =E22*0.2 -> 219.456
A23: Aplicación de coadyuvantes | B23: Hectáreas | C23: 3.81 | D23: 300 | E23: =C23*D23*4 -> 4572 | F23: =E23*0.8 -> 3657.6 | G23: =E23*0.2 -> 914.4
A24: Desmonte o limpieza del terreno | B24: Hectáreas | C24: 3.81 | D24: 1000 | E24: =C24*D24 -> 3810 | F24: =E24*0.8 -> 3048 | G24: =E24*0.2 -> 762
A25: Siembra de semilla | B25: Hectáreas | C25: 3.81 | D25: 1500 | E25: =C25*D25 -> 5715 | F25: =E25*0.8 -> 4572 | G25: =E25*0.2 -> 1143
A26: Rastreo y barbecho | B26: Hectáreas | C26: 3.81 | D26: 1700 | E26: =C26*D26 -> 6477 | F26: =E26*0.8 -> 5181.6 | G26: =E26*0.2 -> 1295.4
A27: Sueldo Jefe departamento de cultivo | B27: Servicio | C27: 1 | D27: 2340 | E27: =C27*D27*12 -> 28080 | F27: =E27*0.8 -> 22464 | G27: =E27*0.2 -> 5616
A28: Sueldo jornalero de cultivo | B28: Servicio | C28: 1 | D28: 1950 | E28: =C28*D28*12 -> 23400 | F28: =E28*0.8 -> 18720 | G28: =E28*0.2 -> 4680
A29: Impuesto sobre nómina | B29: Cargo fiscal | C29: 1 | D29: ='CRONOGRAMA DE ACTIVIDADES'!D21 -> 671.2626 | E29: =D29*12 -> 8055.1512 | F29: =E29*0.8 -> 6444.121 | G29: =E29*0.2 -> 1611.0302
A30: Subtotal | E30: =SUM(E13:E29) -> 180685.53 | F30: =SUM(F13:F29) -> 144548.42 | G30: =SUM(G13:G29) -> 36137.106
A31: TOTAL | E31: =E30 -> 180685.53 | F31: =F30 -> 144548.42 | G31: =G30 -> 36137.106
A32: PORCENTAJE | E32: =+E31/E31 -> 1 | F32: =+F31/E31 -> 0.8 | G32: 0.2
A34: Se siembra en ambos terrenos a la vez
A37: CONCEPTO | B37: COSTO TOTAL | C37: APORTACIÓN
C38: DEPENDENCIA | D38: GRUPO
A39: CAPITAL DE TRABAJO | C39: FIRA 80% | D39: Caña de la Loma 20%
A40: Semilla | B40: 41910 | C40: =B40*0.8 -> 33528 | D40: =B40*0.2 -> 8382
A41: Enraizadores | B41: 29718 | C41: =B41*0.8 -> 23774.4 | D41: =B41*0.2 -> 5943.6
A42: Aplicación de enraizadores | B42: 1143 | C42: =B42*0.8 -> 914.4 | D42: =B42*0.2 -> 228.6
A43: Herbicidas | B43: 10972.8 | C43: =B43*0.8 -> 8778.24 | D43: =B43*0.2 -> 2194.56
A44: Aplicación de herbicidas | B44: 3429 | C44: =B44*0.8 -> 2743.2 | D44: =B44*0.2 -> 685.8
A45: Insecticidas | B45: 1752.6 | C45: =B45*0.8 -> 1402.08 | D45: =B45*0.2 -> 350.52
A46: Aplicación de insecticidas | B46: 4572 | C46: =B46*0.8 -> 3657.6 | D46: =B46*0.2 -> 914.4
A47: Fungicidas | B47: 1409.7 | C47: =B47*0.8 -> 1127.76 | D47: =B47*0.2 -> 281.94
A48: Aplicación de fungicidas | B48: 4572 | C48: =B48*0.8 -> 3657.6 | D48: =B48*0.2 -> 914.4
A49: Coadyuvantes | B49: 1097.28 | C49: =B49*0.8 -> 877.824 | D49: =B49*0.2 -> 219.456
A50: Aplicación de coadyuvantes | B50: 4572 | C50: =B50*0.8 -> 3657.6 | D50: =B50*0.2 -> 914.4
A51: Desmonte o limpieza del terreno | B51: 3810 | C51: =B51*0.8 -> 3048 | D51: =B51*0.2 -> 762
... A55: Sueldo jornalero de cultivo | B55: 23400 | C55: =B55*0.8 -> 18720 | D55: =B55*0.2 -> 4680
A56: Impuesto sobre nómina | B56: =E29 -> 8055.1512 | C56: =B56*0.8 -> 6444.121 | D56: =B56*0.2 -> 1611.0302
A57: TOTAL | B57: =SUM(B40:B56) -> 180685.53 | C57: =SUM(C40:C56) -> 144548.42 | D57: =SUM(D40:D56) -> 36137.106
A58: PORCENTAJE | B58: =+B57/B57 -> 1 | C58: =+C57/B57 -> 0.8 | D58: 0.2

Sheet BALANZA
A1: 1
A2: BANCOS | D2: CUENTAS | E2: SALDOS INICIALES | G2: MOVIMIENTOS | I2: SALDOS | L2: AJUSTES | O2: SALDOS AJUSTADOS
A3: ='AMORTIZACIONES (48)'!M35 -> 197905.14 | B3: DOC X PAGAR LP | E3: D | F3: H | G3: D | H3: H | I3: D | J3: H | L3: D | M3: H | O3: D | P3: H
B4: =A3 -> 197905.14 | D4: Caja y Bancos | E4: 60000 | G4: =A3+A11 -> 577756.96 | H4: =B8+B16+B27+B33+B37 -> 456255.77 | I4: =E4+G4-H4 -> 181501.19
A5: 2 | D5: Inventarios | G5: =A7 -> 86860.38 | I5: =E5+G5-H5 -> 86860.38
A6: INSUMOS (INVENTARIOS) | D6: Terrenos | E6: 1524000 | I6: =E6+G6-H6 -> 1524000
A7: ='CRONOGRAMA DE ACTIVIDADES'!P30 -> 86860.38 | B7: BANCOS | D7: Eq de reparto | I7: =E7+G7-H7 -> 0
B8: =A7 -> 86860.38 | D8: Eq de oficina | I8: =E8+G8-H8 -> 0
A9: 3 | D9: Docs x pagar | F9: 9600 | G9: =A30 -> 36180.015 | H9: =B4 -> 197905.14 | J9: =F9+H9-G9 -> 171325.12
A10: BANCOS | D10: Impuestos | F10: 11864.24 | J10: =F10+H10-G10 -> 11864.24
A11: ='CUADRO DE EGRESOS E INGRESOS'!B40 -> 379851.82 | B11: VENTAS | D11: Aportación incial | F11: 600000 | J11: =F11+H11-G11 -> 600000
B12: ='CUADRO DE EGRESOS E INGRESOS'!B40 -> 379851.82 | D12: Capital Social | F12: 873850.27 | J12: =F12+H12-G12 -> 873850.27
A13: 4 | D13: Utilidades x aplicar | J13: =F13+H13-G13 -> 0
A14: COSTO DE VENTAS | D14: Resultados de ej ant | J14: =F14+H14-G14 -> 0 | M14: =AJUSTES!E29 -> 88685.49 | N14: (7
A15: ='CRONOGRAMA DE ACTIVIDADES'!P31 -> 180685.53 | B15: BANCOS | D15: Utilidad | F15: 88685.49 | J15: =F15+H15-G15 -> 88685.49 | K15: 7) | L15: =AJUSTES!D28 -> 88685.49 | M15: =AJUSTES!E25 -> 10456.433 | N15: (6
B16: =A15 -> 180685.53 | D16: Gastos financieros | G16: =A32 -> 23064.881 | I16: =G16 -> 23064.881 | M16: =AJUSTES!L20 -> 59244.896 | N16: (5
D17: Costo de ventas | G17: =A15 -> 180685.53 | I17: =G17 -> 180685.53 | M17: =AJUSTES!E5 -> 180685.53 | N17: (1
A18: 5 | D18: Gastos fijos | G18: =A20 -> 125666.44 | I18: =G18 -> 125666.44 | M18: =AJUSTES!E13 -> 125666.44 | N18: (3
A19: GASTOS FIJOS | D19: ISR | G19: =A36 -> 3798.5182 | I19: =G19 -> 3798.5182 | M19: =AJUSTES!E17 -> 3798.5182 | N19: (4
A20: ='CUADRO DE EGRESOS E INGRESOS'!O17 -> 125666.44 | B20: BANCOS | D20: Ventas | H20: =B12 -> 379851.82 | J20: =H20 -> 379851.82 | K20: 1) | L20: =AJUSTES!D4 -> 180685.53
K21: 2) | L21: =AJUSTES!D8 -> 199166.29
D22: Perdidas y Ganancias | K22: 5) | L22: =AJUSTES!K14 -> 59244.896 | M22: =AJUSTES!E9 -> 199166.29 | N22: (2
K23: 3) | L23: =AJUSTES!D12 -> 125666.44
K24: 4) | L24: =AJUSTES!D16 -> 3798.5182
K25: 6) | L25: =AJUSTES!D24 -> 10456.433
B27: ='CUADRO DE EGRESOS E INGRESOS'!O17 -> 125666.44 | D27: TOTAL | E27: =E4+E6 -> 1584000 | F27: =SUM(F4:F20) -> 1584000 | G27: =SUM(G4:G20) -> 1034012.7 | H27: =SUM(H4:H20) -> 1034012.7 | I27: =SUM(I4:I20) -> 2125576.9 | J27: =SUM(J4:J20) -> 2125576.9 | L27: =SUM(L4:L26) -> 667703.6 | M27: =SUM(M4:M26) -> 667703.6
A28: 7
A29: DOCS X PAGAR LP
A30: ='AMORTIZACIONES (48)'!K14 -> 36180.015
A31: GASTOS FINANCIEROS
A32: ='AMORTIZACIONES (48)'!L12 -> 23064.881 | B32: BANCOS
B33: =A30+A32 -> 59244.896
A34: 8
A35: ISR
A36: ='CUADRO DE EGRESOS E INGRESOS'!B40*0.01 -> 3798.5182 | B36: BANCOS
B37: =A36 -> 3798.5182

Sheet AJUSTES
B3: 1 | G3: VENTAS | K3: CV | O3: Gastos Fijos
B4: VENTAS | D4: =BALANZA!G17 -> 180685.53 | F4: 1) | G4: =D4 -> 180685.53 | H4: =BALANZA!H20 -> 379851.82 | I4: (S | J4: S) | K4: =BALANZA!G17 -> 180685.53 | L4: =E5 -> 180685.53 | M4: (1 | N4: S) | O4: =BALANZA!G18 -> 125666.44 | P4: =E13 -> 125666.44 | Q4: (3
C5: CV | E5: =BALANZA!G17 -> 180685.53 | F5: 2) | G5: =D8 -> 199166.29
B6: Para determinar la Utilidad Bruta | G6: =SUM(G4:G5) -> 379851.82 | H6: =SUM(H4:H5) -> 379851.82
B7: 2
B8: Ventas | D8: =BALANZA!H20-BALANZA!G17 -> 199166.29
C9: P y G | E9: =D8 -> 199166.29
B10: Para cancelar las ventas del ejercicio
B11: 3 | G11: ISR | K11: P y G | O11: Resultado del Ejerc
B12: P y G | D12: =BALANZA!G18 -> 125666.44 | F12: S) | G12: =BALANZA!G19 -> 3798.5182 | H12: =E17 -> 3798.5182 | I12: (4 | J12: 3) | K12: =D12 -> 125666.44 | L12: =E9 -> 199166.29 | M12: (2 | N12: 7) | O12: =BALANZA!J15 -> 88685.49 | P12: =BALANZA!J15 -> 88685.49 | Q12: (S
C13: Gastos Fijos | E13: =BALANZA!G18 -> 125666.44 | J13: 4) | K13: =D16 -> 3798.5182 | P13: =K16 -> 10456.433 | Q13: (6
B14: Para cancelar los gastos fijos | J14: 5) | K14: =D20 -> 59244.896
B15: 4 | K15: =SUM(K12:K14) -> 188709.85 | L15: =L12 -> 199166.29
B16: P y G | D16: =BALANZA!G19 -> 3798.5182 | J16: 6) | K16: =L15-K15 -> 10456.433
C17: ISR | E17: =BALANZA!G19 -> 3798.5182 | K17: =SUM(K15:K16) -> 199166.29 | L17: =SUM(L15:L16) -> 199166.29
B18: Para disminuir el ISR del ejercicio
B19: 5 | K19: Gastos Financieros | O19: Result. De Ejerc. Anteriores
B20: P y G | D20: =BALANZA!B33 -> 59244.896 | J20: S) | K20: =E21 -> 59244.896 | L20: =K14 -> 59244.896 | M20: (5 | P20: =O12 -> 88685.49 | Q20: (7
C21: Gastos Financieros | E21: =D20 -> 59244.896
B22: Para cancelar los gastos financieros
B23: 6
B24: P y G | D24: =K16 -> 10456.433
C25: Res del Ejerc | E25: =P13 -> 10456.433
B26: Para registrar el Result. Del Ejercicio
B27: 7
B28: Resultado del Ejerc | D28: =O12 -> 88685.49
C29: Result. De Ejerc. Ant | E29: =P20 -> 88685.49
B30: Para traspasar el Res. Del ejercicio anterior

Sheet PROYECCIONES EGRESOS E INGRESOS
A4: 4.9 PUNTO DE EQUILIBRIO
A5: CONCEPTO | B5: AÑO 1 | C5: AÑO 2 | D5: AÑO 3 | E5: AÑO 4 | F5: AÑO 5
A6: INGRESOS | B6: ='CUADRO DE EGRESOS E INGRESOS'!B40 -> 379851.82 | C6: ='CUADRO DE EGRESOS E INGRESOS'!C40 -> 375487.81 | D6: ='CUADRO DE EGRESOS E INGRESOS'!D40 -> 384524.13 | E6: ='CUADRO DE EGRESOS E INGRESOS'!E40 -> 393775.95 | F6: ='CUADRO DE EGRESOS E INGRESOS'!F40 -> 403250.38
H7: =B9/B6 -> 0.47567373
A8: COSTOS DE OPERACION | B8: =B9+B10 -> 306351.97 | C8: =C9+C10 -> 244702.78 | D8: =D9+D10 -> 257159.29 | E8: =E9+E10 -> 271110.5 | F8: =F9+F10 -> 286735.92
A9: COSTOS VARIABLES | B9: ='M. DE CALCULO DE COSTOS VARIABL'!H57 -> 180685.53 | C9: =COSTOS!C53 -> 119036.34 | D9: =COSTOS!D53 -> 131492.85 | E9: =COSTOS!E53 -> 145444.06 | F9: =COSTOS!F53 -> 161069.48
A10: COSTOS FIJOS | B10: ='M. DE CALCULO DE GASTOS FIJOS'!R49 -> 125666.44 | C10: =COSTOS!C71 -> 125666.44 | D10: ='CUADRO DE EGRESOS E INGRESOS'!O32 -> 125666.44 | E10: ='CUADRO DE EGRESOS E INGRESOS'!O32 -> 125666.44 | F10: ='CUADRO DE EGRESOS E INGRESOS'!O32 -> 125666.44
A12: UTILIDAD DE OPERACIÓN | B12: =B6-B8 -> 73499.847 | C12: =C6-C8 -> 130785.03 | D12: =D6-D8 -> 127364.84 | E12: =E6-E8 -> 122665.45 | F12: =F6-F8 -> 116514.46
A14: IMPUESTOS | B14: =B6*0.01 -> 3798.5182 | C14: =C6*1% -> 3754.8781 | D14: =D6*1% -> 3845.2413 | E14: =E6*1% -> 3937.7595 | F14: =F6*1% -> 4032.5038
A15: PAGO CAPITAL | B15: ='AMORTIZACIONES (48)'!L16 -> 59244.896 | C15: ='AMORTIZACIONES (48)'!P11 -> 52732.496 | D15: ='AMORTIZACIONES (48)'!P12 -> 46220.096 | E15: ='AMORTIZACIONES (48)'!P13 -> 39707.696
A16: UTILIDAD NETA | B16: =B12-B14-B15 -> 10456.433 | C16: =C12-C14-C15 -> 74297.658 | D16: =D12-D14-D15 -> 77299.503 | E16: =E12-E14-E15 -> 79019.996 | F16: =F12-F14-F15 -> 112481.95
A18: PUNTO DE EQUILIBRIO | B18: =229.36*B20 -> 232075.66 | C18: =229.36*C20 -> 230738.53 | D18: =229.36*D20 -> 229407.96 | E18: =229.36*E20 -> 228085.07 | F18: =229.36*F20 -> 226769.8
A19: como % de ventas
A20: Precio de venta unitario | B20: ='CUADRO DE EGRESOS E INGRESOS'!I39 -> 1011.8402 | C20: ='CUADRO DE EGRESOS E INGRESOS'!J39 -> 1006.0103 | D20: ='CUADRO DE EGRESOS E INGRESOS'!K39 -> 1000.2091 | E20: ='CUADRO DE EGRESOS E INGRESOS'!L39 -> 994.44136 | F20: ='CUADRO DE EGRESOS E INGRESOS'!M39 -> 988.70686
O21: UNIDADES PRODUCIDAS
A23: UTILIDAD POR SOCIO | B23: =B24+B25 -> 10456.433 | C23: =C24+C25 -> 74297.658 | D23: =D24+D25 -> 77299.503 | E23: =E24+E25 -> 79019.996 | F23: =F24+F25 -> 112481.95 | H23: PRECIO DE VENTA UNIT/TON | K23: 1011.84
A24: Andrés | B24: =B16*0.51 -> 5332.7808 | C24: =C16*0.51 -> 37891.806 | D24: =D16*0.51 -> 39422.747 | E24: =E16*0.51 -> 40300.198 | F24: =F16*0.51 -> 57365.796 | H24: COSTO VTA UNIT/TON | K24: =K23*48% -> 485.6832
A25: Beatriz | B25: =B16*0.49 -> 5123.6521 | C25: =C16*0.49 -> 36405.853 | D25: =D16*0.49 -> 37876.757 | E25: =E16*0.49 -> 38719.798 | F25: =F16*0.49 -> 55116.157 | H25: GASTOS FIJOS | K25: =B10 -> 125666.44
A27: GRÁFICA DEL PUNTO DE EQUILIBRIO | H27: PE UNIDADES | K27: =K25/(K23-K24) -> 238.83838 | L27: =K23 -> 1011.84 | M27: =K27*L27 -> 241666.23
H30: CANTIDAD | I30: VENTAS | J30: COSTOS TOTALES | K30: UTILIDADES
H31: =K27/2 -> 119.41919 | I31: =H31*K$23 -> 120833.12 | J31: =(H31*K$24)+K$25 -> 183666.34 | K31: =I31-J31 -> -62833.22
H32: =K27 -> 238.83838 | I32: =H32*K$23 -> 241666.23 | J32: =(H32*K$24)+K$25 -> 241666.23 | K32: =I32-J32 -> 0
H33: =(H32*50%)+H32 -> 358.25758 | I33: =H33*K$23 -> 362499.35 | J33: =(H33*K$24)+K$25 -> 299666.13 | K33: =I33-J33 -> 62833.22
H34: =(H33*50%)+H33 -> 537.38636 | I34: =H34*K$23 -> 543749.02 | J34: =(H34*K$24)+K$25 -> 386665.97 | K34: =I34-J34 -> 157083.05
A47: Se siembra en ambos terrenos a la vez

Sheet CUADRO DE EGRESOS E INGRESOS
A1: ESTRUCTURA DE INGRESOS Y EGERESOS
A3: SITUACION FINANCIERA ACTUAL Y PROYECTADA
A5: PROYECTO: | B5: Implementación de semilla CP57-536
A6: SOCIEDAD | B6: Caña de la Loma
A7: BENEFICIARIOS:
C8: NOV | D8: DEC | E8: ENE | F8: FEB | G8: MAR | H8: ABR | I8: MAY | J8: JUN | K8: JUL | L8: AGO | M8: SEPT | N8: OCT
A9: FLUJO DE I N G R E S O S Y E G R E S O S
A10: PRIMER AÑO DE INVERSIÓN
A11: C O N C E P T O | C11: 1 MES | D11: 2 MES | E11: 3 MES | F11: 4 MES | G11: 5 MES | H11: 6 MES | I11: 7 MES | J11: 8 MES | K11: 9 MES | L11: 10 MES | M11: 11 MES | N11: 12 MES | O11: TOTAL | Q11: toneladas esperadas por hectarea
A12: INGRESOS POR VENTAS | D12: =Q14*Q17/2 -> 189925.91 | J12: =Q14*Q17/2 -> 189925.91 | O12: =SUM(C12:M12) -> 379851.82 | Q12: 97.4 | U12: 263.006 | W12: =Q14-U12 -> 108.088
A13: TOTAL DE INGRESOS | O13: =O12 -> 379851.82 | Q13: toneladas por 3.81
Q14: =Q12*3.81 -> 371.094 | T14: 371.094
A15: EGRESOS
A16: VARIABLE | C16: ='CRONOGRAMA DE ACTIVIDADES'!D31 -> 98228.158 | D16: ='CRONOGRAMA DE ACTIVIDADES'!E31 -> 4961.2626 | E16: ='CRONOGRAMA DE ACTIVIDADES'!F31 -> 4961.2626 | F16: ='CRONOGRAMA DE ACTIVIDADES'!G31 -> 14255.758 | G16: ='CRONOGRAMA DE ACTIVIDADES'!H31 -> 4961.2626 | H16: ='CRONOGRAMA DE ACTIVIDADES'!I31 -> 4961.2626 | I16: ='CRONOGRAMA DE ACTIVIDADES'!J31 -> 14255.758 | J16: ='CRONOGRAMA DE ACTIVIDADES'!K31 -> 4961.2626 | ... N16: ='CRONOGRAMA DE ACTIVIDADES'!O31 -> 4961.2626 | O16: =SUM(C16:N16) -> 180685.53 | P16: =O16/O12 -> 0.47567373 | Q16: precio 2027
A17: FIJOS | C17: ='M. DE CALCULO DE GASTOS FIJOS'!F48 -> 27341.88 | D17: ='M. DE CALCULO DE GASTOS FIJOS'!G48 -> 4683.6 | E17: ='M. DE CALCULO DE GASTOS FIJOS'!H48 -> 4683.6 | F17: ='M. DE CALCULO DE GASTOS FIJOS'!I48 -> 4683.6 | G17: ='M. DE CALCULO DE GASTOS FIJOS'!J48 -> 4683.6 | H17: ='M. DE CALCULO DE GASTOS FIJOS'!K48 -> 4683.6 | I17: ='M. DE CALCULO DE GASTOS FIJOS'!L48 -> 4683.6 | J17: ='M. DE CALCULO DE GASTOS FIJOS'!M48 -> 4683.6 | ... N17: ='M. DE CALCULO DE GASTOS FIJOS'!Q48 -> 4683.6 | O17: =SUM(C17:N17) -> 125666.44 | Q17: 1023.6
A18: SALDO | C18: =C16+C17 -> 125570.04 | D18: =D16+D17 -> 9644.8626 | E18: =E16+E17 -> 9644.8626 | F18: =F16+F17 -> 18939.358 | G18: =G16+G17 -> 9644.8626 | H18: =H16+H17 -> 9644.8626 | I18: =I16+I17 -> 18939.358 | J18: =J16+J17 -> 9644.8626 | ... N18: =N16+N17 -> 9644.8626 | O18: =SUM(C18:N18) -> 306351.97
A19: SALDO ACUMULADO | C19: =+C18 -> 125570.04 | D19: =D12-D18 -> 180281.05 | E19: =E18 -> 9644.8626 | F19: =F18 -> 18939.358 | G19: =G18 -> 9644.8626 | H19: =H18 -> 9644.8626 | I19: =I18 -> 18939.358 | J19: =J12-J18 -> 180281.05 | K19: =K18 -> 56449.823 | L19: =L18 -> 18939.358 | M19: =M18 -> 9644.8626 | N19: =N18 -> 9644.8626 | O19: =O13-O18 -> 73499.847 | S19: =Q17*Q14 -> 379851.82
A23: PROYECCION FINANCIERA ANUAL
A25: SEGUNDO AÑO DE INVERSIÓN (RESOCA)
A26: C O N C E P T O | C26: 1 MES | D26: 2 MES | E26: 3 MES | F26: 4 MES | G26: 5 MES | H26: 6 MES | I26: 7 MES | J26: 8 MES | K26: 9 MES | L26: 10 MES | M26: 11 MES | N26: 12 MES | O26: TOTAL
A27: INGRESOS POR VENTAS | D27: =O27/2 -> 189925.91 | J27: =O27/2 -> 189925.91 | O27: ='PROYECCIONES EGRESOS E INGRESOS'!B6 -> 379851.82
A28: TOTAL DE INGRESOS | O28: =O27 -> 379851.82
A30: EGRESOS
A31: VARIABLE | C31: =COSTOS!B4 -> 98228.158 | D31: =COSTOS!C4 -> 4961.2626 | E31: =COSTOS!D4 -> 4961.2626 | F31: =COSTOS!E4 -> 14255.758 | G31: =COSTOS!F4 -> 4961.2626 | H31: =COSTOS!G4 -> 4961.2626 | I31: =COSTOS!H4 -> 14255.758 | J31: =COSTOS!I4 -> 4961.2626 | ... N31: =COSTOS!M4 -> 4961.2626 | O31: =SUM(C31:N31) -> 180685.53
A32: FIJOS | C32: =C17 -> 27341.88 | D32: =D17 -> 4683.6 | E32: =E17 -> 4683.6 | F32: =F17 -> 4683.6 | G32: =G17 -> 4683.6 | H32: =H17 -> 4683.6 | I32: =I17 -> 4683.6 | J32: =J17 -> 4683.6 | ... N32: =N17 -> 4683.6 | O32: =SUM(C32:N32) -> 125666.44
A33: SALDO | C33: =C31+C32 -> 125570.04 | D33: =D31+D32 -> 9644.8626 | E33: =E31+E32 -> 9644.8626 | F33: =F31+F32 -> 18939.358 | G33: =G31+G32 -> 9644.8626 | H33: =H31+H32 -> 9644.8626 | I33: =I31+I32 -> 18939.358 | J33: =J31+J32 -> 9644.8626 | ... N33: =N31+N32 -> 9644.8626 | O33: =SUM(C33:N33) -> 306351.97
A34: SALDO ACUMULADO | C34: =C33 -> 125570.04 | D34: =D27-D33 -> 180281.05 | E34: =E33 -> 9644.8626 | F34: =F33 -> 18939.358 | G34: =G33 -> 9644.8626 | H34: =H33 -> 9644.8626 | I34: =I33 -> 18939.358 | J34: =J27+J33 -> 199570.77 | K34: =K33 -> 56449.823 | L34: =L33 -> 18939.358 | M34: =M33 -> 9644.8626 | N34: =N33 -> 9644.8626 | O34: =O28-O33 -> 73499.847
A37: CAPACIDAD DE PAGO | I37: PRECIO
C38: 2027-2028 | D38: 2029-2030 | E38: 2030-2031 | F38: 2031-2032 | G38: 2032-2033 | I38: 2027-2028 | J38: 2029-2030 | K38: 2030-2031 | L38: 2031-2032 | M38: 2032-2033
A39: CONCEPTO | B39: PRMER AÑO | C39: SEGUNDO AÑO | D39: TERCER AÑO | E39: CUARTO AÑO | F39: QUINTO AÑO | G39: SEXTO AÑO | I39: 1011.8402 | J39: 1006.0103 | K39: 1000.2091 | L39: 994.44136 | M39: 988.70686
A40: INGRESOS | B40: =S19 -> 379851.82 | C40: =I39*I43 -> 375487.81 | D40: =J39*J43 -> 384524.13 | E40: =K39*K43 -> 393775.95 | F40: =L39*L43 -> 403250.38 | G40: =M39*M43 -> 412952.76
A41: EGRESOS | B41: =O18 -> 306351.97 | C41: =COSTOS!C97 -> 244702.78 | D41: =COSTOS!D97 -> 257159.29 | E41: =COSTOS!E97 -> 271110.5 | F41: =COSTOS!F97 -> 286735.92 | G41: =COSTOS!G97 -> 302715.39 | I41: VOLUMEN
A42: TOTAL | B42: =O19 -> 73499.847 | C42: =+C40-C41 -> 130785.03 | D42: =+D40-D41 -> 127364.84 | E42: =+E40-E41 -> 122665.45 | F42: =+F40-F41 -> 116514.46 | G42: =G40-G41 -> 110237.37 | I42: 2027-2028 | J42: 2029-2030 | K42: 2030-2031 | L42: 2031-2032 | M42: 2032-2033
C43: =C42-B42 -> 57285.185 | I43: =Q14 -> 371.094 | J43: =I43*1.03 -> 382.22682 | K43: =J43*1.03 -> 393.69362 | L43: =K43*1.03 -> 405.50443 | M43: =L43*1.03 -> 417.66957
A44: Se siembra en ambos terrenos a la vez

Sheet COSTOS
B2: COSTOS DE PRODUCCION AÑO 1
A3: VARIABLES | B3: 1 | C3: 2 | D3: 3 | E3: 4 | F3: 5 | G3: 6 | H3: 7 | I3: 8 | J3: 9 | K3: 10 | L3: 11 | M3: 12 | N3: TOTAL
A4: TOTAL VARIABLES | B4: =SUM(B5:B21) -> 98228.158 | C4: =SUM(C5:C21) -> 4961.2626 | D4: =SUM(D5:D21) -> 4961.2626 | E4: =SUM(E5:E21) -> 14255.758 | F4: =SUM(F5:F21) -> 4961.2626 | G4: =SUM(G5:G21) -> 4961.2626 | H4: =SUM(H5:H21) -> 14255.758 | I4: =SUM(I5:I21) -> 4961.2626 | ... N4: =SUM(N5:N21) -> 180685.53
A5: Desmonte o limpieza del terreno | B5: ='CRONOGRAMA DE ACTIVIDADES'!D11 -> 3810 | N5: =SUM(B5:M5) -> 3810
A6: Rastreo y barbecho | B6: ='CRONOGRAMA DE ACTIVIDADES'!D12 -> 6477 | N6: =SUM(B6:M6) -> 6477
A7: Siembra de semilla | B7: ='CRONOGRAMA DE ACTIVIDADES'!D13 -> 5715 | N7: =SUM(B7:M7) -> 5715
A8: Semillas | B8: ='M. DE CALCULO DE COSTOS VARIABL'!E10 -> 41910 | N8: =SUM(B8:M8) -> 41910
A9: Enraizadores | B9: ='M. DE CALCULO DE COSTOS VARIABL'!E11 -> 29718 | N9: =SUM(B9:M9) -> 29718
A10: Herbicidas | E10: ='CRONOGRAMA DE ACTIVIDADES'!G29 -> 3657.6 | H10: =E10 -> 3657.6 | K10: =H10 -> 3657.6 | N10: =SUM(B10:M10) -> 10972.8
A11: Insecticidas | B11: ='CRONOGRAMA DE ACTIVIDADES'!D25 -> 438.15 | E11: =B11 -> 438.15 | H11: =E11 -> 438.15 | K11: =H11 -> 438.15 | N11: =SUM(B11:M11) -> 1752.6
A12: Funcigidas | B12: ='CRONOGRAMA DE ACTIVIDADES'!D26 -> 352.425 | E12: =B12 -> 352.425 | H12: =E12 -> 352.425 | K12: =H12 -> 352.425 | N12: =SUM(B12:M12) -> 1409.7
A13: Coadyuvantes | B13: ='CRONOGRAMA DE ACTIVIDADES'!D27 -> 274.32 | E13: =B13 -> 274.32 | H13: =B13 -> 274.32 | K13: =B13 -> 274.32 | N13: =SUM(B13:M13) -> 1097.28
A14: Sueldo jefe de departamento de cultivo | B14: ='CRONOGRAMA DE ACTIVIDADES'!D19 -> 2340 | C14: =B14 -> 2340 | D14: =B14 -> 2340 | E14: =B14 -> 2340 | F14: =B14 -> 2340 | G14: =B14 -> 2340 | H14: =B14 -> 2340 | I14: =B14 -> 2340 | J14: =B14 -> 2340 | K14: =B14 -> 2340 | L14: =B14 -> 2340 | M14: =B14 -> 2340 | N14: =SUM(B14:M14) -> 28080
A15: Sueldo jornalero de cultivo | B15: ='CRONOGRAMA DE ACTIVIDADES'!D20 -> 1950 | C15: =B15 -> 1950 | D15: =B15 -> 1950 | E15: =B15 -> 1950 | F15: =B15 -> 1950 | G15: =B15 -> 1950 | H15: =B15 -> 1950 | I15: =B15 -> 1950 | J15: =B15 -> 1950 | K15: =B15 -> 1950 | L15: =B15 -> 1950 | M15: =B15 -> 1950 | N15: =SUM(B15:M15) -> 23400
A16: Aplicación de enraizadores | B16: ='CRONOGRAMA DE ACTIVIDADES'!D14 -> 1143 | N16: =SUM(B16:M16) -> 1143
A17: Aplicación de coadyuvantes | B17: ='CRONOGRAMA DE ACTIVIDADES'!D15 -> 1143 | E17: =B17 -> 1143 | H17: =B17 -> 1143 | K17: =B17 -> 1143 | N17: =SUM(B17:M17) -> 4572
A18: Aplicación de insecticidas | B18: ='CRONOGRAMA DE ACTIVIDADES'!D16 -> 1143 | E18: =B18 -> 1143 | H18: =B18 -> 1143 | K18: =B18 -> 1143 | N18: =SUM(B18:M18) -> 4572
A19: Aplicación de fungicidas | B19: ='CRONOGRAMA DE ACTIVIDADES'!D17 -> 1143 | E19: =B19 -> 1143 | H19: =B19 -> 1143 | K19: =B19 -> 1143 | N19: =SUM(B19:M19) -> 4572
A20: Aplicación de herbicidas | E20: ='CRONOGRAMA DE ACTIVIDADES'!G18 -> 1143 | H20: =E20 -> 1143 | K20: =H20 -> 1143 | N20: =SUM(B20:M20) -> 3429
A21: Impuesto sobre nómina | B21: ='CRONOGRAMA DE ACTIVIDADES'!D21 -> 671.2626 | C21: =B21 -> 671.2626 | D21: =B21 -> 671.2626 | E21: =B21 -> 671.2626 | F21: =B21 -> 671.2626 | G21: =B21 -> 671.2626 | H21: =E21 -> 671.2626 | I21: =B21 -> 671.2626 | J21: =B21 -> 671.2626 | K21: =H21 -> 671.2626 | L21: =B21 -> 671.2626 | M21: =B21 -> 671.2626 | N21: =SUM(B21:M21) -> 8055.1512
A22: TOTAL FIJOS | B22: =SUM(B23:B47) -> 27341.88 | C22: =SUM(C23:C47) -> 4683.6 | D22: =SUM(D23:D47) -> 4683.6 | E22: =SUM(E23:E47) -> 4683.6 | F22: =SUM(F23:F47) -> 4683.6 | G22: =SUM(G23:G47) -> 4683.6 | H22: =SUM(H23:H47) -> 4683.6 | I22: =SUM(I23:I47) -> 4683.6 | ... N22: =SUM(N23:N47) -> 125666.44
A23: Sueldo administradora | B23: ='M. DE CALCULO DE GASTOS FIJOS'!F11 -> 2081.6 | C23: =B23 -> 2081.6 | D23: =B23 -> 2081.6 | E23: =B23 -> 2081.6 | F23: =B23 -> 2081.6 | G23: =B23 -> 2081.6 | H23: =B23 -> 2081.6 | I23: =B23 -> 2081.6 | J23: =B23 -> 2081.6 | K23: =B23 -> 2081.6 | L23: =B23 -> 2081.6 | M23: =B23 -> 2081.6 | N23: =SUM(B23:M23) -> 24979.2
A24: Sueldo contadora | B24: ='M. DE CALCULO DE GASTOS FIJOS'!F12 -> 2602 | C24: =B24 -> 2602 | D24: =B24 -> 2602 | E24: =B24 -> 2602 | F24: =B24 -> 2602 | G24: =B24 -> 2602 | H24: =B24 -> 2602 | I24: =B24 -> 2602 | J24: =B24 -> 2602 | K24: =B24 -> 2602 | L24: =B24 -> 2602 | M24: =B24 -> 2602 | N24: =SUM(B24:M24) -> 31224
A25: Ret.IMSS eventual Preliq | J25: 5701.97 | N25: =SUM(B25:M25) -> 5701.97
A26: Gastos distribuibles de grupo de cosecha | B26: 22658.28 | N26: =SUM(B26:M26) -> 22658.28
A27: Caminos secundarios | J27: 1438.72 | N27: =SUM(B27:M27) -> 1438.72
A28: Caminos generales | J28: 1370.39 | N28: =SUM(B28:M28) -> 1370.39
A29: Comité de producción | J29: 2367.05 | N29: =SUM(B29:M29) -> 2367.05
A30: Gestión remota de NAX | J30: 633.85 | N30: =SUM(B30:M30) -> 633.85
A31: Madurador | J31: 647 | N31: =SUM(B31:M31) -> 647
A32: Cuotas nacionales | J32: 1369.64 | N32: =SUM(B32:M32) -> 1369.64
A33: Incentivo nominal | J33: 920.53 | N33: =SUM(B33:M33) -> 920.53
A34: Despensas | J34: 1078.33 | N34: =SUM(B34:M34) -> 1078.33
A35: Apoyo a Mov. De grupos | J35: 697.83 | N35: =SUM(B35:M35) -> 697.83
A36: Cuota local | J36: 2261.85 | N36: =SUM(B36:M36) -> 2261.85
A37: Cuota IMSS eventual | J37: 523.39 | N37: =SUM(B37:M37) -> 523.39
A38: Ret.Seg de vida CNC | J38: 500 | N38: =SUM(B38:M38) -> 500
... A47: RET CNC | J47: 500 | N47: =SUM(B47:M47) -> 500
A48: TOTAL COSTO OPERACIÓN | B48: =+B22+B4 -> 125570.04 | C48: =+C22+C4 -> 9644.8626 | D48: =+D22+D4 -> 9644.8626 | E48: =+E22+E4 -> 18939.358 | F48: =+F22+F4 -> 9644.8626 | G48: =+G22+G4 -> 9644.8626 | H48: =+H22+H4 -> 18939.358 | I48: =+I22+I4 -> 9644.8626 | ... N48: =+N22+N4 -> 306351.97
A52: VARIABLES | B52: AÑO 1 | C52: AÑO 2 | D52: AÑO 3 | E52: AÑO 4 | F52: AÑO 5 | G52: AÑO 6
A53: TOTAL VARIABLES | B53: =SUM(B54:B70) -> 180685.53 | C53: =SUM(C54:C70) -> 119036.34 | D53: =SUM(D54:D70) -> 131492.85 | E53: =SUM(E54:E70) -> 145444.06 | F53: =SUM(F54:F70) -> 161069.48 | G53: =SUM(G54:G70) -> 177048.95
A54: Desmonte o limpieza del terreno | B54: 3810 | C54: =B54*1.12 -> 4267.2 | D54: =C54*1.12 -> 4779.264 | E54: =D54*1.12 -> 5352.7757 | F54: =E54*1.12 -> 5995.1088 | G54: =F54*1.12 -> 6714.5218
A55: Rastreo y barbecho | B55: 6477 | C55: =B55*1.12 -> 7254.24 | D55: =C55*1.12 -> 8124.7488 | E55: =D55*1.12 -> 9099.7187 | F55: =E55*1.12 -> 10191.685 | G55: =F55*1.12 -> 11414.687
A56: Siembra de semilla | B56: 5715 | C56: =B56*1.12 -> 6400.8 | D56: =C56*1.12 -> 7168.896 | E56: =D56*1.12 -> 8029.1635 | F56: =E56*1.12 -> 8992.6631 | G56: =F56*1.12 -> 10071.783
A57: Semillas | B57: =N8 -> 41910 | C57: N/A | D57: N/A | E57: N/A | F57: N/A | G57: N/A
A58: Enraizadores | B58: =N9 -> 29718 | C58: N/A | D58: N/A | E58: N/A | F58: N/A | G58: N/A
A59: Herbicidas | B59: =N10 -> 10972.8 | C59: =B59 -> 10972.8 | D59: =C59 -> 10972.8 | E59: =D59 -> 10972.8 | F59: =E59 -> 10972.8 | G59: =F59 -> 10972.8
A60: Insecticidas | B60: =N11 -> 1752.6 | C60: =B60 -> 1752.6 | D60: =C60 -> 1752.6 | E60: =D60 -> 1752.6 | F60: =E60 -> 1752.6 | G60: =F60 -> 1752.6
A61: Funcigidas | B61: =N12 -> 1409.7 | C61: =B61 -> 1409.7 | D61: =C61 -> 1409.7 | E61: =D61 -> 1409.7 | F61: =E61 -> 1409.7 | G61: =F61 -> 1409.7
A62: Coadyuvantes | B62: =N13 -> 1097.28 | C62: =B62 -> 1097.28 | D62: =C62 -> 1097.28 | E62: =D62 -> 1097.28 | F62: =E62 -> 1097.28 | G62: =F62 -> 1097.28
A63: Sueldo jefe de departamento de cultivo | B63: =N14 -> 28080 | C63: =B63*1.12 -> 31449.6 | D63: =C63*1.12 -> 35223.552 | E63: =D63*1.12 -> 39450.378 | F63: =E63*1.12 -> 44184.424 | G63: =F63*1.12 -> 49486.554
A64: Sueldo jornalero de cultivo | B64: =N15 -> 23400 | C64: =B64*1.12 -> 26208 | D64: =C64*1.12 -> 29352.96 | E64: =D64*1.12 -> 32875.315 | F64: =E64*1.12 -> 36820.353 | G64: =F64*1.12 -> 41238.795
A65: Aplicación de enraizadores | B65: =N16 -> 1143 | C65: N/A | D65: N/A | E65: N/A | F65: N/A | G65: N/A
A66: Aplicación de coadyuvantes | B66: =N17 -> 4572 | C66: =B66*1.12 -> 5120.64 | D66: =C66*1.12 -> 5735.1168 | E66: =D66*1.12 -> 6423.3308 | F66: =E66*1.12 -> 7194.1305 | G66: =F66*1.12 -> 8057.4262
A67: Aplicación de insecticidas | B67: =N18 -> 4572 | C67: =B67*1.12 -> 5120.64 | D67: =C67*1.12 -> 5735.1168 | E67: =D67*1.12 -> 6423.3308 | F67: =E67*1.12 -> 7194.1305 | G67: =F67*1.12 -> 8057.4262
A68: Aplicación de fungicidas | B68: =N19 -> 4572 | C68: =B68*1.12 -> 5120.64 | D68: =C68*1.12 -> 5735.1168 | E68: =D68*1.12 -> 6423.3308 | F68: =E68*1.12 -> 7194.1305 | G68: =F68*1.12 -> 8057.4262
A69: Aplicación de herbicidas | B69: =N20 -> 3429 | C69: =B69*1.12 -> 3840.48 | D69: =C69*1.12 -> 4301.3376 | E69: =D69*1.12 -> 4817.4981 | F69: =E69*1.12 -> 5395.5979 | G69: =F69*1.12 -> 6043.0696
A70: Impuesto sobre nómina | B70: =N21 -> 8055.1512 | C70: =751.81*12 -> 9021.72 | D70: =842.03*12 -> 10104.36 | E70: =943.07*12 -> 11316.84 | F70: =1056.24*12 -> 12674.88 | G70: =1056.24*12 -> 12674.88
A71: TOTAL FIJOS | B71: =SUM(B72:B96) -> 125666.44 | C71: =SUM(C72:C96) -> 125666.44 | D71: =SUM(D72:D96) -> 125666.44 | E71: =SUM(E72:E96) -> 125666.44 | F71: =SUM(F72:F96) -> 125666.44 | G71: =SUM(G72:G96) -> 125666.44
A72: Sueldo administradora | B72: =N23 -> 24979.2 | C72: =B72 -> 24979.2 | D72: =C72 -> 24979.2 | E72: =D72 -> 24979.2 | F72: =E72 -> 24979.2 | G72: =F72 -> 24979.2
A73: Sueldo contadora | B73: =N24 -> 31224 | C73: =B73 -> 31224 | D73: =C73 -> 31224 | E73: =D73 -> 31224 | F73: =E73 -> 31224 | G73: =F73 -> 31224
A74: Ret.IMSS eventual Preliq | B74: 5701.97 | C74: 5701.97 | D74: 5701.97 | E74: 5701.97 | F74: 5701.97 | G74: 5701.97
A75: Gastos distribuibles de grupo de cosecha | B75: 22658.28 | C75: 22658.28 | D75: 22658.28 | E75: 22658.28 | F75: 22658.28 | G75: 22658.28
A76: Caminos secundarios | B76: 1438.72 | C76: 1438.72 | D76: 1438.72 | E76: 1438.72 | F76: 1438.72 | G76: 1438.72
A77: Caminos generales | B77: 1370.39 | C77: 1370.39 | D77: 1370.39 | E77: 1370.39 | F77: 1370.39 | G77: 1370.39
A78: Comité de producción | B78: 2367.05 | C78: 2367.05 | D78: 2367.05 | E78: 2367.05 | F78: 2367.05 | G78: 2367.05
A79: Gestión remota de NAX | B79: 633.85 | C79: 633.85 | D79: 633.85 | E79: 633.85 | F79: 633.85 | G79: 633.85
A80: Madurador | B80: 647 | C80: 647 | D80: 647 | E80: 647 | F80: 647 | G80: 647
A81: Cuotas nacionales | B81: 1369.64 | C81: 1369.64 | D81: 1369.64 | E81: 1369.64 | F81: 1369.64 | G81: 1369.64
A82: Incentivo nominal | B82: 920.53 | C82: 920.53 | D82: 920.53 | E82: 920.53 | F82: 920.53 | G82: 920.53
A83: Despensas | B83: 1078.33 | C83: 1078.33 | D83: 1078.33 | E83: 1078.33 | F83: 1078.33 | G83: 1078.33
A84: Apoyo a Mov. De grupos | B84: 697.83 | C84: 697.83 | D84: 697.83 | E84: 697.83 | F84: 697.83 | G84: 697.83
A85: Cuota local | B85: 2261.85 | C85: 2261.85 | D85: 2261.85 | E85: 2261.85 | F85: 2261.85 | G85: 2261.85
... A91: Ret. CILDCA-CONADESUCA | B91: 76.27 | C91: 76.27 | D91: 76.27 | E91: 76.27 | F91: 76.27 | G91: 76.27
A92: CUOTAS IMSS EVENTUAL | B92: =N43 -> 523.39 | C92: =B92 -> 523.39 | D92: =C92 -> 523.39 | E92: =D92 -> 523.39 | F92: =E92 -> 523.39 | G92: =F92 -> 523.39
A93: CUOTAS IMSS PRODUCTOR | B93: =N44 -> 11864.24 | C93: =B93 -> 11864.24 | D93: =C93 -> 11864.24 | E93: =D93 -> 11864.24 | F93: =E93 -> 11864.24 | G93: =F93 -> 11864.24
A94: RET CNPR | B94: =N45 -> 447.5 | C94: =B94 -> 447.5 | D94: =C94 -> 447.5 | E94: =D94 -> 447.5 | F94: =E94 -> 447.5 | G94: =F94 -> 447.5
A95: RET CONADESUCA | B95: =N46 -> 76.27 | C95: =B95 -> 76.27 | D95: =C95 -> 76.27 | E95: =D95 -> 76.27 | F95: =E95 -> 76.27 | G95: =F95 -> 76.27
A96: RET CNC | B96: =N47 -> 500 | C96: =B96 -> 500 | D96: =C96 -> 500 | E96: =D96 -> 500 | F96: =E96 -> 500 | G96: =F96 -> 500
A97: TOTAL COSTO OPERACIÓN | B97: =SUM(B71+B53) -> 306351.97 | C97: =+C71+C53 -> 244702.78 | D97: =SUM(D71+D53) -> 257159.29 | E97: =SUM(E71+E53) -> 271110.5 | F97: =SUM(F71+F53) -> 286735.92 | G97: =SUM(G71+G53) -> 302715.39
A99: Se siembra en ambos terrenos a la vez

Sheet M. DE CALCULO DE COSTOS VARIABL
A1: ESTRUCTURA DE INGRESOS Y EGERESOS
A3: MEMORIAS DE CALCULO COSTOS VARIABLES
A5: PROYECTO: | B5: Implementación de semilla CP57-536
A6: SOCIEDAD | B6: Caña de la Loma
A7: BENEFICIARIOS:
A8: MEMORIA DE CALCULO MATERIA PRIMA E INSUMOS (MENSUAL)
B9: MEDIDA | C9: CANT (ha) | D9: C.U. | E9: TOTAL (3.81 ha)
A10: Semillas | B10: Toneladas | C10: 10 | D10: 1100 | E10: =C10*D10*3.81 -> 41910
A11: Enraizadores | B11: Costales | C11: =6 -> 6 | D11: ='ESTRUCTURA FINANCIERA'!D14 -> 1300 | E11: =C11*D11*3.81 -> 29718
A12: Herbicidas | B12: Litros | C12: =8 -> 8 | D12: 120 | E12: =C12*D12*3.81 -> 3657.6
A13: Insecticidas | B13: Litros | C13: 1 | D13: ='ESTRUCTURA FINANCIERA'!D18 -> 115 | E13: =C13*D13*3.81 -> 438.15
A14: Funcigidas | B14: Litros | C14: 1 | D14: ='ESTRUCTURA FINANCIERA'!D20 -> 92.5 | E14: =C14*D14*3.81 -> 352.425
A15: Coadyuvantes | B15: Litros | C15: 1 | D15: ='ESTRUCTURA FINANCIERA'!D22 -> 72 | E15: =C15*D15*3.81 -> 274.32
A16: Subtotal | E16: =SUM(E10:E15) -> 76350.495
A18: MEMORIA DE CALCULO DE MOD (MENSUAL)
B19: MEDIDA | C19: CANT | D19: C.U. | E19: TOTAL
A20: Desmonte o limpieza del terreno | B20: Servicio | C20: 1 | D20: 1000 | E20: =D20*3.81 -> 3810
A21: Rastreo y barbecho | B21: Servicio | C21: 1 | D21: 1700 | E21: =D21*3.81 -> 6477
A22: Siembra de semilla | B22: Servicio | C22: 1 | D22: 1500 | E22: =D22*3.81 -> 5715
A23: Sueldo jefe de departamento de cultivo | B23: Servicio | C23: 1 | D23: 2340 | E23: =D23 -> 2340 | F23: 12 meses
A24: Sueldo jornalero de cultivo | B24: Servicio | C24: 1 | D24: 1950 | E24: =D24 -> 1950 | F24: 12 meses
A25: Aplicación de enraizadores | B25: Servicio | C25: 1 | D25: 300 | E25: =D25*3.81 -> 1143 | F25: Nov, feb, may y ago
A26: Aplicación de coadyuvantes | B26: Servicio | C26: 1 | D26: 300 | E26: =D26*3.81 -> 1143 | F26: Nov, feb, may y ago
A27: Aplicación de insecticidas | B27: Servicio | C27: 1 | D27: 300 | E27: =D27*3.81 -> 1143 | F27: Nov, feb, may y ago
A28: Aplicación de fungicidas | B28: Servicio | C28: 1 | D28: 300 | E28: =D28*3.81 -> 1143 | F28: Nov, feb, may y ago
A29: Aplicación de herbicidas | B29: Servicio | C29: 1 | D29: 300 | E29: =D29*3.81 -> 1143 | F29: Feb, may y ago
A30: Impuesto sobre nómina | B30: Servicio | C30: 1 | D30: ='CRONOGRAMA DE ACTIVIDADES'!D21 -> 671.2626 | E30: =D30 -> 671.2626 | F30: 12 meses
A31: Subtotal | E31: =SUM(E23:E30) -> 10676.263 | G31: TOTAL MENSUAL | H31: =E16+E31 -> 87026.758
A34: MEMORIA DE CALCULO MATERIA PRIMA E INSUMOS (ANUAL)
B35: MEDIDA | C35: CANT (ha) | D35: C.U. | E35: TOTAL (3.81 ha)
A36: Semillas | B36: Toneladas | C36: 10 | D36: 1100 | E36: =C36*D36*3.81 -> 41910
A37: Enraizadores | B37: Costales | C37: 6 | D37: 1300 | E37: =C37*D37*3.81 -> 29718
A38: Herbicidas | B38: Litros | C38: =8 -> 8 | D38: =D12 -> 120 | E38: =C38*D38*3.81*3 -> 10972.8
A39: Insecticidas | B39: Litros | C39: 1 | D39: ='ESTRUCTURA FINANCIERA'!D18 -> 115 | E39: =C39*D39*3.81*4 -> 1752.6
A40: Funcigidas | B40: Litros | C40: 1 | D40: ='ESTRUCTURA FINANCIERA'!D20 -> 92.5 | E40: =C40*D40*3.81*4 -> 1409.7
A41: Coadyuvantes | B41: Litros | C41: 1 | D41: ='ESTRUCTURA FINANCIERA'!D22 -> 72 | E41: =C41*D41*3.81*4 -> 1097.28
A42: Subtotal | E42: =SUM(E36:E41) -> 86860.38
A44: MEMORIA DE CALCULO DE MOD (ANUAL)
B45: MEDIDA | C45: CANT | D45: C.U. | E45: TOTAL
A46: Desmonte o limpieza del terreno | B46: Servicio | C46: 1 | D46: 1000 | E46: =D46*3.81 -> 3810
A47: Rastreo y barbecho | B47: Servicio | C47: 1 | D47: 1700 | E47: =D47*3.81 -> 6477
A48: Siembra de semilla | B48: Servicio | C48: 1 | D48: 1500 | E48: =D48*3.81 -> 5715
A49: Sueldo jefe de departamento de cultivo | B49: Servicio | C49: 1 | D49: 2340 | E49: =D49*12 -> 28080
A50: Sueldo jornalero de cultivo | B50: Servicio | C50: 1 | D50: 1950 | E50: =D50*12 -> 23400
A51: Aplicación de enraizadores | B51: Servicio | C51: 1 | D51: 300 | E51: =D51*3.81 -> 1143
A52: Aplicación de coadyuvantes | B52: Servicio | C52: 1 | D52: 300 | E52: =D52*3.81*4 -> 4572
A53: Aplicación de insecticidas | B53: Servicio | C53: 1 | D53: 300 | E53: =D53*3.81*4 -> 4572
A54: Aplicación de fungicidas | B54: Servicio | C54: 1 | D54: 300 | E54: =D54*3.81*4 -> 4572
A55: Aplicación de herbicidas | B55: Servicio | C55: 1 | D55: 300 | E55: =D55*3.81*3 -> 3429
A56: Impuesto sobre nómina | B56: Servicio | C56: 1 | D56: =D30 -> 671.2626 | E56: =D56*12 -> 8055.1512
A57: Subtotal | E57: =SUM(E46:E56) -> 93825.151 | G57: TOTAL ANUAL | H57: =E42+E57 -> 180685.53 | I57: =H57/3.81 -> 47424.024
A61: Se siembra en ambos terrenos a la vez

Sheet M. DE CALCULO DE GASTOS FIJOS
A1: ESTRUCTURA DE INGRESOS Y EGERESOS
A3: MEMORIAS DE CALCULO GASTOS FIJOS
A5: PROYECTO: | B5: Implementación de semilla CP57-536
A6: SOCIEDAD | B6: Caña de la Loma | F6: NOV | G6: DEC | H6: ENE | I6: FEB | J6: MAR | K6: ABR | L6: MAY | M6: JUN | N6: JUL | O6: AGO | P6: SEPT | Q6: OCT
A7: BENEFICIARIOS:
A9: MEMORIA DE CALCULO GASTOS GENERALES | F9: MESES
B10: MEDIDA | C10: CANT | D10: C.U. | E10: TOTAL | F10: 1 | G10: 2 | H10: 3 | I10: 4 | J10: 5 | K10: 6 | L10: 7 | M10: 8 | N10: 9 | O10: 10 | P10: 11 | Q10: 12 | T10: GASTOS FIJOS
A11: SUELDO ADMINISTRADORA | B11: EVENTUAL | C11: 1 | D11: 2081.6 | E11: =C11*D11 -> 2081.6 | F11: =E11 -> 2081.6 | G11: =F11 -> 2081.6 | H11: =G11 -> 2081.6 | I11: =H11 -> 2081.6 | J11: =I11 -> 2081.6 | K11: =J11 -> 2081.6 | L11: =K11 -> 2081.6 | M11: =L11 -> 2081.6 | ... Q11: =P11 -> 2081.6
A12: SUELDO CONTADORA | B12: EVENTUAL | C12: 1 | D12: 2602 | E12: =C12*D12 -> 2602 | F12: =E12 -> 2602 | G12: =F12 -> 2602 | H12: =G12 -> 2602 | I12: =H12 -> 2602 | J12: =I12 -> 2602 | K12: =J12 -> 2602 | L12: =K12 -> 2602 | M12: =L12 -> 2602 | ... Q12: =P12 -> 2602 | T12: GASTOS GENERALES | U12: =R13 -> 56203.2
A13: Subtotal | F13: =SUM(F11:F12) -> 4683.6 | G13: =SUM(G11:G12) -> 4683.6 | H13: =SUM(H11:H12) -> 4683.6 | I13: =SUM(I11:I12) -> 4683.6 | J13: =SUM(J11:J12) -> 4683.6 | K13: =SUM(K11:K12) -> 4683.6 | L13: =SUM(L11:L12) -> 4683.6 | M13: =SUM(M11:M12) -> 4683.6 | ... Q13: =SUM(Q11:Q12) -> 4683.6 | R13: =SUM(F13:Q13) -> 56203.2 | T13: GASTOS SOCIALES | U13: =R24 -> 13411.4
T14: GASTOS INVERSIÓN FIJA | U14: =R47 -> 56051.84
T15: TOTAL | U15: =SUM(U12:U14) -> 125666.44
A16: MEMORIA DE CALCULO GASTOS SOCIALES | F16: MESES
F17: 1 | G17: 2 | H17: 3 | I17: 4 | J17: 5 | K17: 6 | L17: 7 | M17: 8 | N17: 9 | O17: 10 | P17: 11 | Q17: 12
A18: CUOTAS IMSS EVENTUAL | N18: 523.39
A19: CUOTAS IMSS PRODUCTOR | N19: 11864.24
A20: RET CNPR | N20: 447.5
A21: RET CONADESUCA | N21: 76.27
A22: RET CNC | N22: 500
A24: Subtotal | N24: =SUM(N18:N23) -> 13411.4 | R24: =SUM(F24:Q24) -> 13411.4
A27: MEMORIA DE CALCULO GASTOS FIJOS PARA LA INVERSION FIJA | F27: MESES
A28: CONCEPTO | B28: MEDIDA | C28: CANT | D28: C.U. | E28: TOTAL | F28: 1 | G28: 2 | H28: 3 | I28: 4 | J28: 5 | K28: 6 | L28: 7 | M28: 8 | N28: 9 | O28: 10 | P28: 11 | Q28: 12
A29: Ret.IMSS eventual Preliq | B29: Servicio | C29: 1 | D29: 5701.97 | E29: 5701.97 | N29: 5701.97
A30: Gastos distribuibles de grupo de cosecha | B30: Servicio | C30: 1 | D30: 22658.28 | E30: 22658.28 | F30: =E30 -> 22658.28
A31: Caminos secundarios | B31: Servicio | C31: 1 | D31: 1438.72 | E31: 1438.72 | N31: 1438.72
A32: Caminos generales | B32: Servicio | C32: 1 | D32: 1370.39 | E32: 1370.39 | N32: 1370.39
A33: Comité de producción | B33: Servicio | C33: 1 | D33: 2367.05 | E33: 2367.05 | N33: 2367.05
A34: Gestión remota de NAX | B34: Servicio | C34: 1 | D34: 633.85 | E34: 633.85 | N34: 633.85
A35: Madurador | B35: Servicio | C35: 1 | D35: 647 | E35: 647 | N35: 647
A36: Cuotas nacionales | B36: Servicio | C36: 1 | D36: 1369.64 | E36: 1369.64 | N36: 1369.64
A37: Incentivo nominal | B37: Servicio | C37: 1 | D37: 920.53 | E37: 920.53 | N37: 920.53
A38: Despensas | B38: Servicio | C38: 1 | D38: 1078.33 | E38: 1078.33 | N38: 1078.33
A39: Apoyo a Mov. De grupos | B39: Servicio | C39: 1 | D39: 697.83 | E39: 697.83 | N39: 697.83
A40: Cuota local | B40: Servicio | C40: 1 | D40: 2261.85 | E40: 2261.85 | N40: 2261.85
A41: Cuota IMSS eventual | B41: Servicio | C41: 1 | D41: 523.39 | E41: 523.39 | N41: 523.39
A42: Ret.Seg de vida CNC | B42: Servicio | C42: 1 | D42: 500 | E42: 500 | N42: 500
... A46: Ret. CILDCA-CONADESUCA | B46: Servicio | C46: 1 | D46: 76.27 | E46: 76.27 | N46: 76.27
A47: Subtotal | F47: =SUM(F29:F46) -> 22658.28 | N47: =SUM(N29:N46) -> 33393.56 | R47: =SUM(F47:Q47) -> 56051.84
F48: =F13+F24+F47 -> 27341.88 | G48: =G13+G24+G47 -> 4683.6 | H48: =H13+H24+H47 -> 4683.6 | I48: =I13+I24+I47 -> 4683.6 | J48: =J13+J24+J47 -> 4683.6 | K48: =K13+K24+K47 -> 4683.6 | L48: =L13+L24+L47 -> 4683.6 | M48: =M13+M24+M47 -> 4683.6 | ... Q48: =Q13+Q24+Q47 -> 4683.6
F49: Nov | G49: Dic | H49: Ene | I49: Feb | J49: Mar | K49: Abr | L49: May | M49: Jun | N49: Jul | O49: Ago | P49: Sep | Q49: Oct | R49: =SUM(R13:R47) -> 125666.44
A50: Se siembra en ambos terrenos a la vez

Sheet INGRESOS
A2: MEMORIAS DE INGRESOS
A4: PROYECTO: | B4: Implementación de CP57-536
A5: SOCIEDAD | B5: Caña de la Loma
A6: BENEFICIARIOS: | B6: NOV | C6: DEC | D6: ENE | E6: FEB | F6: MAR | G6: ABR | H6: MAY | I6: JUN | J6: JUL | K6: AGO | L6: SEPT | M6: OCT
A8: CONCEPTOS | B8: INGRESOS POR VENTA MENSUAL AÑO 1
A9: MES | B9: 1 | C9: 2 | D9: 3 | E9: 4 | F9: 5 | G9: 6 | H9: 7 | I9: 8 | J9: 9 | K9: 10 | L9: 11 | M9: 12 | N9: TOTAL
A10: INGRESOS POR VENTAS | N10: ANUAL
A11: TOTAL DE INGRESOS | C11: ='CUADRO DE EGRESOS E INGRESOS'!D27 -> 189925.91 | I11: =C11 -> 189925.91 | N11: =SUM(C11+I11) -> 379851.82
A13: CONCEPTOS | B13: INGRESOS POR VENTA MENSUAL AÑO 2
A14: MES | B14: 1 | C14: 2 | D14: 3 | E14: 4 | F14: 5 | G14: 6 | H14: 7 | I14: 8 | J14: 9 | K14: 10 | L14: 11 | M14: 12 | N14: TOTAL
A15: INGRESOS POR VENTAS | N15: ANUAL
A16: TOTAL DE INGRESOS | C16: ='CUADRO DE EGRESOS E INGRESOS'!C40/2 -> 187743.91 | I16: =375487.81/2 -> 187743.9 | N16: ='CUADRO DE EGRESOS E INGRESOS'!C40 -> 375487.81
A18: CONCEPTOS | B18: INGRESOS POR VENTA MENSUAL AÑO 3
A19: MES | B19: 1 | C19: 2 | D19: 3 | E19: 4 | F19: 5 | G19: 6 | H19: 7 | I19: 8 | J19: 9 | K19: 10 | L19: 11 | M19: 12 | N19: TOTAL
A20: INGRESOS POR VENTAS | N20: ANUAL
A21: TOTAL DE INGRESOS | C21: ='CUADRO DE EGRESOS E INGRESOS'!D40/2 -> 192262.06 | I21: =C21 -> 192262.06 | N21: ='CUADRO DE EGRESOS E INGRESOS'!D40 -> 384524.13
A23: CONCEPTOS | B23: INGRESOS POR VENTA MENSUAL AÑO 4
A24: MES | B24: 1 | C24: 2 | D24: 3 | E24: 4 | F24: 5 | G24: 6 | H24: 7 | I24: 8 | J24: 9 | K24: 10 | L24: 11 | M24: 12 | N24: TOTAL
A25: INGRESOS POR VENTAS | N25: ANUAL
A26: TOTAL DE INGRESOS | C26: ='CUADRO DE EGRESOS E INGRESOS'!E40/2 -> 196887.98 | I26: =C26 -> 196887.98 | N26: ='CUADRO DE EGRESOS E INGRESOS'!E40 -> 393775.95
A28: Se siembra en ambos terrenos a la vez

Sheet DEPRECIACIONES
A1: CALCULO DE DEPRECIACIONES Y AMORTIZACIONES
A3: PROYECTO: | B3: Implementación de CP57-536
A4: SOCIEDAD | B4: Caña de la Loma
A7: MUEBLES Y EQUIPO | B7: VALOR | C7: VIDA UTIL (AÑOS) | D7: TASA DE DEPREC. | E7: DEPRECIACION (ANUAL) | F7: DEPRECIACION (MENSUAL) | G7: DEPRC. ACUM | H7: REMANENTE
A18: MAQUINARIA | B18: VALOR | C18: VIDA UTIL (AÑOS) | D18: TASA DE DEPREC. | E18: DEPRECIACION (ANUAL) | F18: DEPRECIACION (MENSUAL) | G18: DEPRC. ACUM | H18: REMANENTE
A28: Se siembra en ambos terrenos a la vez

Sheet AMORTIZACIONES (48)
A1: AMORTIZACIÓN DE LA DEUDA
A3: PROYECTO: | C3: Implementación de CP57-536
A4: SOCIEDAD | C4: Caña de la Loma
A5: BENEFICIARIOS:
A6: TABLA DE AMORTIZACION DE LA DEUDA
H7: 144720.74
A8: MESES | B8: TASA DE INTERES | C8: INTERES | D8: DEUDA ACUMULADA | E8: PAGO CAPITAL | F8: PAGO INTERES | G8: PAGO TOTAL | H8: SALDO | I8: FECHAS DE PAGO
A9: 1 | B9: =M30/12 -> 0.015 | C9: =B9*H7 -> 2170.8111 | D9: =C9+H7 -> 146891.55 | E9: =H7/48 -> 3015.0154 | F9: =C9 -> 2170.8111 | G9: =F9+E9 -> 5185.8265 | H9: =D9-G9 -> 141705.72
A10: 2 | B10: =M30/12 -> 0.015 | C10: =H9*$B$9 -> 2125.5859 | D10: =H9+C10 -> 143831.31 | E10: 3015 | F10: =C10 -> 2125.5859 | G10: =F10+E10 -> 5140.5859 | H10: =H9-E10 -> 138690.72 | N10: Pago | O10: Interés | P10: Total
A11: 3 | B11: =M30/12 -> 0.015 | C11: =H10*$B$9 -> 2080.3609 | D11: =H10+C11 -> 140771.09 | E11: 3015 | F11: =C11 -> 2080.3609 | G11: =F11+E11 -> 5095.3609 | H11: =H10-E11 -> 135675.72 | M11: Año 2 | N11: =K14 -> 36180.015 | O11: =SUM(C21:C32) -> 16552.48 | P11: =N11+O11 -> 52732.496
A12: 4 | B12: =M30/12 -> 0.015 | C12: =H11*$B$9 -> 2035.1359 | D12: =H11+C12 -> 137710.86 | E12: 3015 | F12: =C12 -> 2035.1359 | G12: =F12+E12 -> 5050.1359 | H12: =H11-E12 -> 132660.72 | L12: =SUM(C9:C20) -> 23064.881 | M12: Año 3 | N12: =N11 -> 36180.015 | O12: =SUM(C33:C44) -> 10040.08 | P12: =N12+O12 -> 46220.096
A13: 5 | B13: =M30/12 -> 0.015 | C13: =H12*$B$9 -> 1989.9109 | D13: =H12+C13 -> 134650.64 | E13: 3015 | F13: =C13 -> 1989.9109 | G13: =F13+E13 -> 5004.9109 | H13: =H12-E13 -> 129645.72 | M13: Año 4 | N13: =N12 -> 36180.015 | O13: =SUM(C45:C56) -> 3527.6804 | P13: =N13+O13 -> 39707.696
A14: 6 | B14: =M30/12 -> 0.015 | C14: =H13*$B$9 -> 1944.6859 | D14: =H13+C14 -> 131590.41 | E14: 3015 | F14: =C14 -> 1944.6859 | G14: =F14+E14 -> 4959.6859 | H14: =H13-E14 -> 126630.72 | K14: =H7-H20 -> 36180.015
A15: 7 | B15: =M30/12 -> 0.015 | C15: =H14*$B$9 -> 1899.4609 | D15: =H14+C15 -> 128530.19 | E15: 3015 | F15: =C15 -> 1899.4609 | G15: =F15+E15 -> 4914.4609 | H15: =H14-E15 -> 123615.72
A16: 8 | B16: =M30/12 -> 0.015 | C16: =H15*$B$9 -> 1854.2359 | D16: =H15+C16 -> 125469.96 | E16: 3015 | F16: =C16 -> 1854.2359 | G16: =F16+E16 -> 4869.2359 | H16: =H15-E16 -> 120600.72 | K16: PAGO 1ER AÑO: | L16: =K14+L12 -> 59244.896
A17: 9 | B17: =M30/12 -> 0.015 | C17: =H16*$B$9 -> 1809.0109 | D17: =H16+C17 -> 122409.74 | E17: 3015 | F17: =C17 -> 1809.0109 | G17: =F17+E17 -> 4824.0109 | H17: =H16-E17 -> 117585.72
A18: 10 | B18: =M30/12 -> 0.015 | C18: =H17*$B$9 -> 1763.7859 | D18: =H17+C18 -> 119349.51 | E18: 3015 | F18: =C18 -> 1763.7859 | G18: =F18+E18 -> 4778.7859 | H18: =H17-E18 -> 114570.72
A19: 11 | B19: =M30/12 -> 0.015 | C19: =H18*$B$9 -> 1718.5609 | D19: =H18+C19 -> 116289.29 | E19: 3015 | F19: =C19 -> 1718.5609 | G19: =F19+E19 -> 4733.5609 | H19: =H18-E19 -> 111555.72
A20: 12 | B20: =M30/12 -> 0.015 | C20: =H19*$B$9 -> 1673.3359 | D20: =H19+C20 -> 113229.06 | E20: 3015 | F20: =C20 -> 1673.3359 | G20: =F20+E20 -> 4688.3359 | H20: =H19-E20 -> 108540.72
A21: 13 | B21: =M30/12 -> 0.015 | C21: =H20*$B$9 -> 1628.1109 | D21: =H20+C21 -> 110168.84 | E21: 3015 | F21: =C21 -> 1628.1109 | G21: =F21+E21 -> 4643.1109 | H21: =H20-E21 -> 105525.72
A22: 14 | B22: =M30/12 -> 0.015 | C22: =H21*$B$9 -> 1582.8859 | D22: =H21+C22 -> 107108.61 | E22: 3015 | F22: =C22 -> 1582.8859 | G22: =F22+E22 -> 4597.8859 | H22: =H21-E22 -> 102510.72 | K22: Se siembra en ambos terrenos a la vez
A23: 15 | B23: =M30/12 -> 0.015 | C23: =H22*$B$9 -> 1537.6609 | D23: =H22+C23 -> 104048.39 | E23: 3015 | F23: =C23 -> 1537.6609 | G23: =F23+E23 -> 4552.6609 | H23: =H22-E23 -> 99495.725
A24: 16 | B24: =M30/12 -> 0.015 | C24: =H23*$B$9 -> 1492.4359 | D24: =H23+C24 -> 100988.16 | E24: 3015 | F24: =C24 -> 1492.4359 | G24: =F24+E24 -> 4507.4359 | H24: =H23-E24 -> 96480.725 | K24: PRIMERA ADMINISTRACIÓN
A25: 17 | B25: =M30/12 -> 0.015 | C25: =H24*$B$9 -> 1447.2109 | D25: =H24+C25 -> 97927.935 | E25: 3015 | F25: =C25 -> 1447.2109 | G25: =F25+E25 -> 4462.2109 | H25: =H24-E25 -> 93465.725 | K25: MONTO: | L25: =H7 -> 144720.74
A26: 18 | B26: =M30/12 -> 0.015 | C26: =H25*$B$9 -> 1401.9859 | D26: =H25+C26 -> 94867.71 | E26: 3015 | F26: =C26 -> 1401.9859 | G26: =F26+E26 -> 4416.9859 | H26: =H25-E26 -> 90450.725 | K26: FECHA: | L26: PRIMER AÑO
A27: =A26+1 -> 19 | B27: =M30/12 -> 0.015 | C27: =H26*$B$9 -> 1356.7609 | D27: =H26+C27 -> 91807.485 | E27: 3015 | F27: =C27 -> 1356.7609 | G27: =F27+E27 -> 4371.7609 | H27: =H26-E27 -> 87435.725
A28: =A27+1 -> 20 | B28: =M30/12 -> 0.015 | C28: =H27*$B$9 -> 1311.5359 | D28: =H27+C28 -> 88747.26 | E28: 3015 | F28: =C28 -> 1311.5359 | G28: =F28+E28 -> 4326.5359 | H28: =H27-E28 -> 84420.725 | L28: DATOS FIRA
A29: =A28+1 -> 21 | B29: =M30/12 -> 0.015 | C29: =H28*$B$9 -> 1266.3109 | D29: =H28+C29 -> 85687.035 | E29: 3015 | F29: =C29 -> 1266.3109 | G29: =F29+E29 -> 4281.3109 | H29: =H28-E29 -> 81405.725 | L29: MESES | M29: 18
A30: =A29+1 -> 22 | B30: =M$30/12 -> 0.015 | C30: =H29*$B$9 -> 1221.0859 | D30: =H29+C30 -> 82626.81 | E30: 3015 | F30: =C30 -> 1221.0859 | G30: =F30+E30 -> 4236.0859 | H30: =H29-E30 -> 78390.725 | L30: Tasa de interes anual | M30: 0.18
A31: =A30+1 -> 23 | B31: =M$30/12 -> 0.015 | C31: =H30*$B$9 -> 1175.8609 | D31: =H30+C31 -> 79566.585 | E31: 3015 | F31: =C31 -> 1175.8609 | G31: =F31+E31 -> 4190.8609 | H31: =H30-E31 -> 75375.725 | L31: Tasa de interes mensual | M31: =M30/12 -> 0.015
A32: =A31+1 -> 24 | B32: =M$30/12 -> 0.015 | C32: =H31*$B$9 -> 1130.6359 | D32: =H31+C32 -> 76506.36 | E32: 3015 | F32: =C32 -> 1130.6359 | G32: =F32+E32 -> 4145.6359 | H32: =H31-E32 -> 72360.725
A33: =A32+1 -> 25 | B33: =M$30/12 -> 0.015 | C33: =H32*$B$9 -> 1085.4109 | D33: =H32+C33 -> 73446.135 | E33: 3015 | F33: =C33 -> 1085.4109 | G33: =F33+E33 -> 4100.4109 | H33: =H32-E33 -> 69345.725 | K33: PAGO DE CAPITAL A 48 MESES | M33: =E10*47 -> 141705
A34: =A33+1 -> 26 | B34: =M$30/12 -> 0.015 | C34: =H33*$B$9 -> 1040.1859 | D34: =H33+C34 -> 70385.91 | E34: 3015 | F34: =C34 -> 1040.1859 | G34: =F34+E34 -> 4055.1859 | H34: =H33-E34 -> 66330.725
A35: =A34+1 -> 27 | B35: =M$30/12 -> 0.015 | C35: =H34*$B$9 -> 994.96087 | D35: =H34+C35 -> 67325.685 | E35: 3015 | F35: =C35 -> 994.96087 | G35: =F35+E35 -> 4009.9609 | H35: =H34-E35 -> 63315.725 | K35: PAGO TOTAL DEL CRÉDITO | M35: =E57+C57 -> 197905.14
A36: =A35+1 -> 28 | B36: =M$30/12 -> 0.015 | C36: =H35*$B$9 -> 949.73587 | D36: =H35+C36 -> 64265.46 | E36: 3015 | F36: =C36 -> 949.73587 | G36: =F36+E36 -> 3964.7359 | H36: =H35-E36 -> 60300.725
A37: =A36+1 -> 29 | B37: =M$30/12 -> 0.015 | C37: =H36*$B$9 -> 904.51087 | D37: =H36+C37 -> 61205.235 | E37: 3015 | F37: =C37 -> 904.51087 | G37: =F37+E37 -> 3919.5109 | H37: =H36-E37 -> 57285.725 | M37: =M35-H7 -> 53184.397
A38: =A37+1 -> 30 | B38: =M$30/12 -> 0.015 | C38: =H37*$B$9 -> 859.28587 | D38: =H37+C38 -> 58145.01 | E38: 3015 | F38: =C38 -> 859.28587 | G38: =F38+E38 -> 3874.2859 | H38: =H37-E38 -> 54270.725
A39: =A38+1 -> 31 | B39: =M$30/12 -> 0.015 | C39: =H38*$B$9 -> 814.06087 | D39: =H38+C39 -> 55084.785 | E39: 3015 | F39: =C39 -> 814.06087 | G39: =F39+E39 -> 3829.0609 | H39: =H38-E39 -> 51255.725
A40: =A39+1 -> 32 | B40: =M$30/12 -> 0.015 | C40: =H39*$B$9 -> 768.83587 | D40: =H39+C40 -> 52024.56 | E40: 3015 | F40: =C40 -> 768.83587 | G40: =F40+E40 -> 3783.8359 | H40: =H39-E40 -> 48240.725
A41: =A40+1 -> 33 | B41: =M$30/12 -> 0.015 | C41: =H40*$B$9 -> 723.61087 | D41: =H40+C41 -> 48964.335 | E41: 3015 | F41: =C41 -> 723.61087 | G41: =F41+E41 -> 3738.6109 | H41: =H40-E41 -> 45225.725
A42: =A41+1 -> 34 | B42: =M$30/12 -> 0.015 | C42: =H41*$B$9 -> 678.38587 | D42: =H41+C42 -> 45904.11 | E42: 3015 | F42: =C42 -> 678.38587 | G42: =F42+E42 -> 3693.3859 | H42: =H41-E42 -> 42210.725
A43: =A42+1 -> 35 | B43: =M$30/12 -> 0.015 | C43: =H42*$B$9 -> 633.16087 | D43: =H42+C43 -> 42843.885 | E43: 3015 | F43: =C43 -> 633.16087 | G43: =F43+E43 -> 3648.1609 | H43: =H42-E43 -> 39195.725
A44: =A43+1 -> 36 | B44: =M$30/12 -> 0.015 | C44: =H43*$B$9 -> 587.93587 | D44: =H43+C44 -> 39783.66 | E44: 3015 | F44: =C44 -> 587.93587 | G44: =F44+E44 -> 3602.9359 | H44: =H43-E44 -> 36180.725
A45: =A44+1 -> 37 | B45: =M$30/12 -> 0.015 | C45: =H44*$B$9 -> 542.71087 | D45: =H44+C45 -> 36723.435 | E45: 3015 | F45: =C45 -> 542.71087 | G45: =F45+E45 -> 3557.7109 | H45: =H44-E45 -> 33165.725
A46: =A45+1 -> 38 | B46: =M$30/12 -> 0.015 | C46: =H45*$B$9 -> 497.48587 | D46: =H45+C46 -> 33663.21 | E46: 3015 | F46: =C46 -> 497.48587 | G46: =F46+E46 -> 3512.4859 | H46: =H45-E46 -> 30150.725
A47: =A46+1 -> 39 | B47: =M$30/12 -> 0.015 | C47: =H46*$B$9 -> 452.26087 | D47: =H46+C47 -> 30602.985 | E47: 3015 | F47: =C47 -> 452.26087 | G47: =F47+E47 -> 3467.2609 | H47: =H46-E47 -> 27135.725
A48: =A47+1 -> 40 | B48: =M$30/12 -> 0.015 | C48: =H47*$B$9 -> 407.03587 | D48: =H47+C48 -> 27542.76 | E48: 3015 | F48: =C48 -> 407.03587 | G48: =F48+E48 -> 3422.0359 | H48: =H47-E48 -> 24120.725
A49: =A48+1 -> 41 | B49: =M$30/12 -> 0.015 | C49: =H48*$B$9 -> 361.81087 | D49: =H48+C49 -> 24482.535 | E49: 3015 | F49: =C49 -> 361.81087 | G49: =F49+E49 -> 3376.8109 | H49: =H48-E49 -> 21105.725
... A56: =A55+1 -> 48 | B56: =M$30/12 -> 0.015 | C56: =H55*$B$9 -> 45.235869 | D56: =H55+C56 -> 3060.9605 | E56: 3015 | F56: =C56 -> 45.235869 | G56: =F56+E56 -> 3060.2359 | H56: =H55-E56 -> 0.72458333
A57: TOTAL | C57: =SUM(C9:C56) -> 53185.122 | D57: =SUM(D9:D56) -> 3598859.9 | E57: =SUM(E9:E56) -> 144720.02 | F57: =SUM(F9:F56) -> 53185.122 | G57: =SUM(G9:G56) -> 197905.14 | H57: =SUM(H9:H56) -> 3400954.8
A61: TABLA DE AMORTIZACION DE LA DEUDA
I62: =H7 -> 144720.74
A63: MESES | B63: TASA DE INTERES | C63: INTERES | D63: DEUDA ACUMULADA | E63: PAGO CAPITAL | F63: PAGO INTERES | G63: PAGO TOTAL | H63: SALDO | I63: FECHAS DE PAGO
A64: 12 | B64: 0.18 | C64: =I62*B$64 -> 26049.733 | D64: =I62+C64 -> 170770.47 | E64: =I62/4 -> 36180.185 | F64: =C64 -> 26049.733 | G64: =E64+F64 -> 62229.918 | H64: =D64-G64 -> 108540.55
A65: =12*2 -> 24 | B65: 0.18 | C65: =H64*B$64 -> 19537.3 | D65: =C65+H64 -> 128077.85 | E65: =I62/4 -> 36180.185 | F65: =C65 -> 19537.3 | G65: =F65+E65 -> 55717.485 | H65: =D65-G65 -> 72360.37
A66: =12*3 -> 36 | B66: 0.18 | C66: =H65*B66 -> 13024.867 | D66: =H65+C66 -> 85385.237 | E66: =I62/4 -> 36180.185 | F66: =C66 -> 13024.867 | G66: =F66+E66 -> 49205.052 | H66: =D66-G66 -> 36180.185
A67: =12*4 -> 48 | B67: 0.18 | C67: =H66*B67 -> 6512.4333 | D67: =H66+C67 -> 42692.618 | E67: =I62/4 -> 36180.185 | F67: =C67 -> 6512.4333 | G67: =F67+E67 -> 42692.618 | H67: =D67-G67 -> 0
A68: TOTAL | C68: =SUM(C64:C67) -> 65124.333 | D68: =H67 -> 0 | E68: =SUM(E64:E67) -> 144720.74 | F68: =SUM(F64:F67) -> 65124.333 | G68: 0 | H68: =H67-E68 -> -144720.74
E69: =SUM(E9:E56) -> 144720.02 | F69: =SUM(F64:F67) -> 65124.333
F70: =E69+F69 -> 209844.35
C75: =(C65+E65)-D64 -> -115052.99

Sheet SENSIBILIDAD
A1: SENSIBILIZACIÓN
A3: PROYECTO: | B3: Implementación de CP57-536
A4: SOCIEDAD | B4: Caña de la Loma
A5: BENEFICIARIOS:
A6: PARA EL PRIMER AÑO
C7: CAMBIO EN VENTAS | G7: CAMBIO EN COSTOS
A8: CONCEPTO | B8: TOTAL PROYECTO | C8: 0.05 | D8: 0.1 | E8: 0.15 | F8: 0.2 | G8: 0.05 | H8: 0.1 | I8: 0.15 | J8: 0.2
A9: VENTAS | B9: ='CUADRO DE EGRESOS E INGRESOS'!O13 -> 379851.82 | C9: =B9*1.05 -> 398844.41 | D9: =B9*1.1 -> 417837 | E9: =B9*1.15 -> 436829.59 | F9: =B9*1.2 -> 455822.18 | G9: 379851.82 | H9: 379851.82 | I9: 379851.82 | J9: 379851.82
A10: COSTOS TOTALES | B10: ='CUADRO DE EGRESOS E INGRESOS'!O18 -> 306351.97 | C10: 216963.13 | D10: 216963.13 | E10: 216963.13 | F10: 216963.13 | G10: =B10*1.05 -> 321669.57 | H10: =B10*1.1 -> 336987.17 | I10: =G10*1.15 -> 369920.01 | J10: =G10*1.2 -> 386003.48
A11: TOTAL | B11: =SUM(B9-B10) -> 73499.847 | C11: =C9-C10 -> 181881.27 | D11: =D9-D10 -> 200873.87 | E11: =E9-E10 -> 219866.46 | F11: =F9-F10 -> 238859.05 | G11: =G9-G10 -> 58182.249 | H11: =H9-H10 -> 42864.65 | I11: =I9-I10 -> 9931.8132 | J11: =J9-J10 -> -6151.6653
A13: RELACION B/C | B13: =+B9/B10 -> 1.2399196 | C13: =+C9/C10 -> 1.838305 | D13: =+D9/D10 -> 1.9258433 | E13: =+E9/E10 -> 2.0133816 | F13: =+F9/F10 -> 2.10092 | G13: =+G9/G10 -> 1.1808758 | H13: =+H9/H10 -> 1.1271997 | I13: =+I9/I10 -> 1.0268485 | J13: =+J9/J10 -> 0.98406319
A15: PARA EL SEGUNDO AÑO
C16: CAMBIO EN VENTAS | G16: CAMBIO EN COSTOS
A17: CONCEPTO | B17: TOTAL PROYECTO | C17: 0.05 | D17: 0.1 | E17: 0.15 | F17: 0.2 | G17: 0.05 | H17: 0.1 | I17: 0.15 | J17: 0.2
A18: VENTAS | B18: ='CUADRO DE EGRESOS E INGRESOS'!O28 -> 379851.82 | C18: =B18*1.5 -> 569777.73 | D18: =B18*1.1 -> 417837 | E18: =B18*1.15 -> 436829.59 | F18: =B18*1.2 -> 455822.18 | G18: =B18 -> 379851.82 | H18: =B18 -> 379851.82 | I18: =B18 -> 379851.82 | J18: =B18 -> 379851.82
A19: COSTOS TOTALES | B19: ='CUADRO DE EGRESOS E INGRESOS'!O33 -> 306351.97 | C19: =B19 -> 306351.97 | D19: =B19 -> 306351.97 | E19: =B19 -> 306351.97 | F19: =B19 -> 306351.97 | G19: =B19*1.05 -> 321669.57 | H19: =B19*1.1 -> 336987.17 | I19: =B19*1.15 -> 352304.77 | J19: =B19*1.2 -> 367622.37
A20: TOTAL | B20: =SUM(B18-B19) -> 73499.847 | C20: =C18-C19 -> 263425.76 | D20: =D18-D19 -> 111485.03 | E20: =E18-E19 -> 130477.62 | F20: =F18-F19 -> 149470.21 | G20: =G18-G19 -> 58182.249 | H20: =H18-H19 -> 42864.65 | I20: =I18-I19 -> 27547.052 | J20: =J18-J19 -> 12229.453
A22: RELACION B/C | B22: =+B18/B19 -> 1.2399196 | C22: =+C18/C19 -> 1.8598794 | D22: =+D18/D19 -> 1.3639116 | E22: =+E18/E19 -> 1.4259076 | F22: =+F18/F19 -> 1.4879035 | G22: =+G18/G19 -> 1.1808758 | H22: =+H18/H19 -> 1.1271997 | I22: =+I18/I19 -> 1.078191 | J22: =+J18/J19 -> 1.0332663
A25: PARA EL TERCER AÑO
C26: CAMBIO EN VENTAS | G26: CAMBIO EN COSTOS
A27: CONCEPTO | B27: TOTAL PROYECTO | C27: 0.05 | D27: 0.1 | E27: 0.15 | F27: 0.2 | G27: 0.05 | H27: 0.1 | I27: 0.15 | J27: 0.2
A28: VENTAS | B28: ='CUADRO DE EGRESOS E INGRESOS'!D40 -> 384524.13 | C28: =B28*1.05 -> 403750.34 | D28: =B28*1.1 -> 422976.54 | E28: =B28*1.15 -> 442202.75 | F28: =B28*1.2 -> 461428.96 | G28: 373324.4 | H28: 373324.4 | I28: 373324.4 | J28: 373324.4
A29: COSTOS TOTALES | B29: ='CUADRO DE EGRESOS E INGRESOS'!D41 -> 257159.29 | C29: =B29 -> 257159.29 | D29: =B29 -> 257159.29 | E29: =B29 -> 257159.29 | F29: =B29 -> 257159.29 | G29: =B29*1.05 -> 270017.25 | H29: =B29*1.1 -> 282875.22 | I29: =B29*1.15 -> 295733.18 | J29: =B29*1.2 -> 308591.15
A30: TOTAL | B30: =SUM(B28-B29) -> 127364.84 | C30: =C28-C29 -> 146591.05 | D30: =D28-D29 -> 165817.25 | E30: =E28-E29 -> 185043.46 | F30: =F28-F29 -> 204269.67 | G30: =G28-G29 -> 103307.14 | H30: =H28-H29 -> 90449.18 | I30: =I28-I29 -> 77591.215 | J30: =J28-J29 -> 64733.251
A32: RELACION B/C | B32: =+B28/B29 -> 1.4952761 | C32: =+C28/C29 -> 1.5700399 | D32: =+D28/D29 -> 1.6448037 | E32: =+E28/E29 -> 1.7195675 | F32: =+F28/F29 -> 1.7943313 | G32: =+G28/G29 -> 1.3825946 | H32: =+H28/H29 -> 1.3197494 | I32: =+I28/I29 -> 1.262369 | J32: =+J28/J29 -> 1.2097703
A36: PARA EL CUARTO AÑO
C37: CAMBIO EN VENTAS | G37: CAMBIO EN COSTOS
A38: CONCEPTO | B38: TOTAL PROYECTO | C38: 0.05 | D38: 0.1 | E38: 0.15 | F38: 0.2 | G38: 0.05 | H38: 0.1 | I38: 0.15 | J38: 0.2
A39: VENTAS | B39: ='CUADRO DE EGRESOS E INGRESOS'!E40 -> 393775.95 | C39: =B39*1.05 -> 413464.75 | D39: =B39*1.1 -> 433153.55 | E39: =B39*1.15 -> 452842.35 | F39: =B39*1.2 -> 472531.14 | G39: 371171.6 | H39: 371171.6 | I39: 371171.6 | J39: 371171.6
A40: COSTOS TOTALES | B40: ='CUADRO DE EGRESOS E INGRESOS'!E41 -> 271110.5 | C40: =B40 -> 271110.5 | D40: =B40 -> 271110.5 | E40: =B40 -> 271110.5 | F40: =B40 -> 271110.5 | G40: =B40*1.05 -> 284666.03 | H40: =B40*1.1 -> 298221.55 | I40: =B40*1.15 -> 311777.08 | J40: =B40*1.2 -> 325332.6
A41: TOTAL | B41: =B39-B40 -> 122665.45 | C41: =C39-C40 -> 142354.25 | D41: =D39-D40 -> 162043.05 | E41: =E39-E40 -> 181731.84 | F41: =F39-F40 -> 201420.64 | G41: =G39-G40 -> 86505.575 | H41: =H39-H40 -> 72950.05 | I41: =I39-I40 -> 59394.525 | J41: =J39-J40 -> 45839
A43: RELACION B/C | B43: =+B39/B40 -> 1.4524555 | C43: =+C39/C40 -> 1.5250783 | D43: =+D39/D40 -> 1.5977011 | E43: =+E39/E40 -> 1.6703239 | F43: =+F39/F40 -> 1.7429467 | G43: =+G39/G40 -> 1.3038844 | H43: =+H39/H40 -> 1.244617 | I43: =+I39/I40 -> 1.1905032 | J43: =+J39/J40 -> 1.1408989
A47: PARA EL QUINTO AÑO
C48: CAMBIO EN VENTAS | G48: CAMBIO EN COSTOS
A49: CONCEPTO | B49: TOTAL PROYECTO | C49: 0.05 | D49: 0.1 | E49: 0.15 | F49: 0.2 | G49: 0.05 | H49: 0.1 | I49: 0.15 | J49: 0.2
A50: VENTAS | B50: ='CUADRO DE EGRESOS E INGRESOS'!F40 -> 403250.38 | C50: =B50*1.05 -> 423412.9 | D50: =B50*1.1 -> 443575.42 | E50: =B50*1.15 -> 463737.94 | F50: =B50*1.2 -> 483900.45 | G50: 369031.22 | H50: 369031.22 | I50: 369031.22 | J50: 369031.22
A51: COSTOS TOTALES | B51: ='CUADRO DE EGRESOS E INGRESOS'!F41 -> 286735.92 | C51: =B51 -> 286735.92 | D51: =B51 -> 286735.92 | E51: =B51 -> 286735.92 | F51: =B51 -> 286735.92 | G51: =B51*1.05 -> 301072.72 | H51: =B51*1.1 -> 315409.52 | I51: =B51*1.15 -> 329746.31 | J51: =B51*1.2 -> 344083.11
A52: TOTAL | B52: =B50-B51 -> 116514.46 | C52: =C50-C51 -> 136676.98 | D52: =D50-D51 -> 156839.49 | E52: =E50-E51 -> 177002.01 | F52: =F50-F51 -> 197164.53 | G52: =G50-G51 -> 67958.502 | H52: =H50-H51 -> 53621.706 | I52: =I50-I51 -> 39284.91 | J52: =J50-J51 -> 24948.114
A54: RELACION B/C | B54: =+B50/B51 -> 1.4063476 | C54: =+C50/C51 -> 1.476665 | D54: =+D50/D51 -> 1.5469824 | E54: =+E50/E51 -> 1.6172997 | F54: =+F50/F51 -> 1.6876171 | G54: =+G50/G51 -> 1.2257212 | H54: =+H50/H51 -> 1.1700066 | I54: =+I50/I51 -> 1.1191368 | J54: =+J50/J51 -> 1.0725061
B57: Se siembra en ambos terrenos a la vez

Sheet TIR - VAN
B2: VAN, TIR Y B/C
C4: TASA DE ACTUALIZACIÓN | E4: 0.15
C6: AÑO | D6: INGRESOS | E6: COSTOS | F6: FLUJO DE EFECTIVO | G6: TASA | H6: INGRESOS | I6: EGRESOS
G7: (1+t)-n | H7: ACTUALIZADOS | I7: ACTUALIZADOS
C8: 0 | D8: =INGRESOS!N11 -> 379851.82 | E8: ='CUADRO DE EGRESOS E INGRESOS'!O18 -> 306351.97 | F8: =D8-E8 -> 73499.847 | G8: =1/(1+$E$4)^C8 -> 1 | H8: =G8*D8 -> 379851.82 | I8: =G8*E8 -> 306351.97
C9: 1 | D9: =INGRESOS!N16 -> 375487.81 | E9: ='CUADRO DE EGRESOS E INGRESOS'!O33 -> 306351.97 | F9: =D9-E9 -> 69135.841 | G9: =1/(1+$E$4)^C9 -> 0.86956522 | H9: =G9*D9 -> 326511.14 | I9: =G9*E9 -> 266393.02 | J9: =H9/I9 -> 1.2256745
C10: 2 | D10: =INGRESOS!N21 -> 384524.13 | E10: ='CUADRO DE EGRESOS E INGRESOS'!D41 -> 257159.29 | F10: =D10-E10 -> 127364.84 | G10: =1/(1+$E$4)^C10 -> 0.75614367 | H10: =G10*D10 -> 290755.49 | I10: =G10*E10 -> 194449.37 | J10: =H10/I10 -> 1.4952761
C11: 3 | D11: =INGRESOS!N26 -> 393775.95 | E11: ='CUADRO DE EGRESOS E INGRESOS'!E41 -> 271110.5 | F11: =D11-E11 -> 122665.45 | G11: =1/(1+$E$4)^C11 -> 0.65751623 | H11: =G11*D11 -> 258914.08 | I11: =G11*E11 -> 178259.56 | J11: =H11/I11 -> 1.4524555
C12: 4 | D12: ='CUADRO DE EGRESOS E INGRESOS'!F40 -> 403250.38 | E12: ='CUADRO DE EGRESOS E INGRESOS'!F41 -> 286735.92 | F12: =D12-E12 -> 116514.46 | G12: =1/(1+$E$4)^C12 -> 0.57175325 | H12: =G12*D12 -> 230559.71 | I12: =G12*E12 -> 163942.19 | J12: =H12/I12 -> 1.4063476
C13: 5 | D13: ='CUADRO DE EGRESOS E INGRESOS'!G40 -> 412952.76 | E13: ='CUADRO DE EGRESOS E INGRESOS'!G41 -> 302715.39 | F13: =D13-E13 -> 110237.37 | G13: =1/(1+$E$4)^C13 -> 0.49717674 | H13: =G13*D13 -> 205310.51 | I13: =G13*E13 -> 150503.05 | J13: =H13/I13 -> 1.3641618
C14: TOTAL | D14: =SUM(D8:D13) -> 2349842.9 | E14: =SUM(E8:E13) -> 1730425 | H14: =SUM(H8:H13) -> 1691902.7 | I14: =SUM(I8:I13) -> 1259899.2 | J14: =SUM(J9:J13) -> 6.9439155
F17: VAN | G17: =H14-I14 -> 432003.59
F18: TIR | G18: 0.15
F19: B/C | G19: =H14/I14 -> 1.3428874
C23: Se siembra en ambos terrenos a la vez

Sheet BALANCE GENERAL PROFORMA
A3: BALANCE GENERAL PROFORMA
A4: CONCEPTO FIJO | B4: AÑO 1 | C4: AÑO 2 | D4: AÑO 3 | E4: AÑO 4
A5: ACTIVO CIRCULANTE
A7: Total activo circulante | B7: =+'CUADRO DE EGRESOS E INGRESOS'!B42 -> 73499.847 | C7: =+C6 -> 0 | D7: =+D6 -> 0 | E7: =+E6 -> 0
A9: ACTIVO FIJO
A32: TOTAL DE ACTIVO FIJO | B32: =+DEPRECIACIONES!#REF! -> #REF! | C32: =+B32/10+B32 -> #REF! | D32: =+B32/10+C32 -> #REF! | E32: =+B32/10+D32 -> #REF!
B33: =SUM(B10:B32) -> #REF! | C33: =SUM(C10:C32) -> #REF! | D33: =SUM(D10:D32) -> #REF! | E33: =SUM(E10:E32) -> #REF!
A34: PASIVO
A36: TOTAL PASIVO
A37: CAPITAL CONTABLE
A42: Se siembra en ambos terrenos a la vez

Sheet ESTADO DE RESULTADOS
B48: Se siembra en ambos terrenos a la vez

Sheet CRONOGRAMA DE ACTIVIDADES
B1: CRONOGRAMA DE ACTIVIDADES
B3: PROYECTO: | C3: Implementación de CP57-536
B4: SOCIEDAD | C4: Caña de la Loma
B5: BENEFICIARIOS:
D6: NOV | E6: DEC | F6: ENE | G6: FEB | H6: MAR | I6: ABR | J6: MAY | K6: JUN | L6: JUL | M6: AGO | N6: SEPT | O6: OCT
B7: CRONOGRAMA DE ACTIVIDADES - PLANTA
C8: 3.81 | D8: MES
B9: CONCEPTO | C9: COSTO HA | D9: 1 | E9: 2 | F9: 3 | G9: 4 | H9: 5 | I9: 6 | J9: 7 | K9: 8 | L9: 9 | M9: 10 | N9: 11 | O9: 12 | P9: TOTAL
B10: 1. LABORES CULTURALES | C10: =SUM(P11:P21) -> 93825.151
B11: Desmonte o limpieza del terreno | C11: 1000 | D11: =C11*C8 -> 3810 | P11: =D11 -> 3810
B12: Rastreo y barbecho | C12: 1700 | D12: =C12*C8 -> 6477 | P12: =D12 -> 6477
B13: Siembra de semilla | C13: 1500 | D13: =C13*C8 -> 5715 | P13: =D13 -> 5715 | Q13: =SUM(P11:P13) -> 16002
B14: Aplicación de enraizadores | C14: 300 | D14: =C14*C8 -> 1143 | P14: =D14 -> 1143
B15: Aplicación de coadyuvantes | C15: 300 | D15: =C15*C8 -> 1143 | G15: =D15 -> 1143 | J15: =C15*C8 -> 1143 | M15: =C15*C8 -> 1143 | P15: =D15+G15+J15+M15 -> 4572
B16: Aplicación de insecticidas | C16: 300 | D16: =C16*C8 -> 1143 | G16: =D16 -> 1143 | J16: =G16 -> 1143 | M16: =D16 -> 1143 | P16: =D16+G16+J16+M16 -> 4572
B17: Aplicación de fungicidas | C17: 300 | D17: =C17*C8 -> 1143 | G17: =C17*C8 -> 1143 | J17: =C17*C8 -> 1143 | M17: =D17 -> 1143 | P17: =D17+G17+J17+M17 -> 4572
B18: Aplicación de herbicidas | C18: 300 | G18: =C18*C8 -> 1143 | J18: =C18*C8 -> 1143 | M18: =C18*C8 -> 1143 | P18: =SUM(D18:O18) -> 3429 | Q18: =SUM(P14:P18) -> 18288
B19: Sueldo Jefe departamento de cultivo | C19: 614.17323 | D19: =C19*C8 -> 2340 | E19: =D19 -> 2340 | F19: =D19 -> 2340 | G19: =D19 -> 2340 | H19: =D19 -> 2340 | I19: =D19 -> 2340 | J19: =D19 -> 2340 | K19: =D19 -> 2340 | L19: =D19 -> 2340 | M19: =D19 -> 2340 | N19: =D19 -> 2340 | O19: =D19 -> 2340 | P19: =SUM(D19:O19) -> 28080
B20: Sueldo jornalero de cultivo | C20: 511.81102 | D20: =C20*C8 -> 1950 | E20: =D20 -> 1950 | F20: =D20 -> 1950 | G20: =D20 -> 1950 | H20: =D20 -> 1950 | I20: =D20 -> 1950 | J20: =D20 -> 1950 | K20: =D20 -> 1950 | L20: =D20 -> 1950 | M20: =D20 -> 1950 | N20: =D20 -> 1950 | O20: =D20 -> 1950 | P20: =SUM(D20:O20) -> 23400
B21: Impuesto sobre nómina | D21: ='CÁLCULO NÓMINA'!K13+'CÁLCULO NÓMINA'!K35 -> 671.2626 | E21: =D21 -> 671.2626 | F21: =D21 -> 671.2626 | G21: =D21 -> 671.2626 | H21: =D21 -> 671.2626 | I21: =D21 -> 671.2626 | J21: =D21 -> 671.2626 | K21: =D21 -> 671.2626 | L21: =D21 -> 671.2626 | M21: =D21 -> 671.2626 | N21: =D21 -> 671.2626 | O21: =D21 -> 671.2626 | P21: =SUM(D21:O21) -> 8055.1512
D22: =SUM(D11:D21) -> 25535.263 | E22: =SUM(E10:E21) -> 4961.2626 | F22: =SUM(F10:F21) -> 4961.2626 | G22: =SUM(G10:G21) -> 9533.2626 | H22: =SUM(H10:H21) -> 4961.2626 | I22: =SUM(I10:I21) -> 4961.2626 | J22: =SUM(J10:J21) -> 9533.2626 | K22: =SUM(K10:K21) -> 4961.2626 | L22: =SUM(L10:L21) -> 4961.2626 | ... O22: =SUM(O10:O21) -> 4961.2626 | P22: =SUM(P11:P21) -> 93825.151
B23: 2. VALOR DE INSUMOS | C23: =SUM(P24:P29) -> 86860.38
B24: Enraizador | C24: =1300*6 -> 7800 | D24: =C24*C8 -> 29718 | P24: =D24 -> 29718
B25: Insecticida | C25: =115 -> 115 | D25: =C25*C8 -> 438.15 | G25: =C25*C8 -> 438.15 | J25: =D25 -> 438.15 | M25: =D25 -> 438.15 | P25: =D25*4 -> 1752.6
B26: Fungicida | C26: =92.5 -> 92.5 | D26: =C26*C8 -> 352.425 | G26: =D26 -> 352.425 | J26: =D26 -> 352.425 | M26: =D26 -> 352.425 | P26: =D26*4 -> 1409.7
B27: Coadyuvantes | C27: =72 -> 72 | D27: =C27*C8 -> 274.32 | G27: =D27 -> 274.32 | J27: =D27 -> 274.32 | M27: =D27 -> 274.32 | P27: =D27*4 -> 1097.28
B28: Semilla | C28: 11000 | D28: =C28*C8 -> 41910 | P28: =D28 -> 41910
B29: Herbicida | C29: =120*8 -> 960 | G29: =C29*C8 -> 3657.6 | J29: =G29 -> 3657.6 | M29: =G29 -> 3657.6 | P29: =SUM(G29:M29) -> 10972.8
D30: =SUM(D24:D29) -> 72692.895 | E30: =SUM(E24:E29) -> 0 | F30: =SUM(F24:F29) -> 0 | G30: =SUM(G24:G29) -> 4722.495 | H30: =SUM(H24:H29) -> 0 | I30: =SUM(I24:I29) -> 0 | J30: =SUM(J24:J29) -> 4722.495 | K30: =SUM(K24:K29) -> 0 | ... P30: =SUM(P24:P29) -> 86860.38
D31: =D22+D30 -> 98228.158 | E31: =E22+E30 -> 4961.2626 | F31: =F22+F30 -> 4961.2626 | G31: =G22+G30 -> 14255.758 | H31: =H22+H30 -> 4961.2626 | I31: =I22+I30 -> 4961.2626 | J31: =J22+J30 -> 14255.758 | K31: =K22+K30 -> 4961.2626 | ... P31: =P22+P30 -> 180685.53
D33: NOV | E33: DEC | F33: ENE | G33: FEB | H33: MAR | I33: ABR | J33: MAY | K33: JUN | L33: JUL | M33: AGO | N33: SEPT | O33: OCT
B34: CRONOGRAMA DE ACTIVIDADES - SOCA
C35: 3.81 | D35: MES
B36: CONCEPTO | C36: COSTO HA | D36: 1 | E36: 2 | F36: 3 | G36: 4 | H36: 5 | I36: 6 | J36: 7 | K36: 8 | L36: 9 | M36: 10 | N36: 11 | O36: 12 | P36: TOTAL
B37: 1. LABORES CULTURALES | C37: =SUM(P38:P46) -> 88110.151
B38: Desmonte o limpieza del terreno | C38: 1000 | D38: =C38*C35 -> 3810 | P38: =D38 -> 3810
B39: Rastreo y barbecho | C39: 1700 | D39: =C39*C35 -> 6477 | P39: =D39 -> 6477
B40: Aplicación de coadyuvantes | C40: 300 | D40: =C40*C35 -> 1143 | G40: =D40 -> 1143 | J40: =C40*C35 -> 1143 | M40: =C40*C35 -> 1143 | P40: =D40+G40+J40+M40 -> 4572
B41: Aplicación de insecticidas | C41: 300 | D41: =C41*C35 -> 1143 | G41: =D41 -> 1143 | J41: =G41 -> 1143 | M41: =D41 -> 1143 | P41: =D41+G41+J41+M41 -> 4572
B42: Aplicación de fungicidas | C42: 300 | D42: =C42*C35 -> 1143 | G42: =C42*C35 -> 1143 | J42: =C42*C35 -> 1143 | M42: =D42 -> 1143 | P42: =D42+G42+J42+M42 -> 4572
B43: Aplicación de herbicidas | C43: 300 | D43: =G43 -> 1143 | G43: =C43*C35 -> 1143 | J43: =C43*C35 -> 1143 | M43: =C43*C35 -> 1143 | P43: =SUM(D43:O43) -> 4572
B44: Sueldo Jefe departamento de cultivo | C44: 614.17323 | D44: =C44*C35 -> 2340 | E44: =D44 -> 2340 | F44: =D44 -> 2340 | G44: =D44 -> 2340 | H44: =D44 -> 2340 | I44: =D44 -> 2340 | J44: =D44 -> 2340 | K44: =D44 -> 2340 | L44: =D44 -> 2340 | M44: =D44 -> 2340 | N44: =D44 -> 2340 | O44: =D44 -> 2340 | P44: =SUM(D44:O44) -> 28080
B45: Sueldo jornalero de cultivo | C45: 511.81102 | D45: =C45*C35 -> 1950 | E45: =D45 -> 1950 | F45: =D45 -> 1950 | G45: =D45 -> 1950 | H45: =D45 -> 1950 | I45: =D45 -> 1950 | J45: =D45 -> 1950 | K45: =D45 -> 1950 | L45: =D45 -> 1950 | M45: =D45 -> 1950 | N45: =D45 -> 1950 | O45: =D45 -> 1950 | P45: =SUM(D45:O45) -> 23400
B46: Impuesto sobre nómina | D46: ='CÁLCULO NÓMINA'!K13+'CÁLCULO NÓMINA'!K35 -> 671.2626 | E46: =D46 -> 671.2626 | F46: =D46 -> 671.2626 | G46: =D46 -> 671.2626 | H46: =D46 -> 671.2626 | I46: =D46 -> 671.2626 | J46: =D46 -> 671.2626 | K46: =D46 -> 671.2626 | L46: =D46 -> 671.2626 | M46: =D46 -> 671.2626 | N46: =D46 -> 671.2626 | O46: =D46 -> 671.2626 | P46: =SUM(D46:O46) -> 8055.1512
D47: =SUM(D38:D46) -> 19820.263 | E47: =SUM(E37:E46) -> 4961.2626 | F47: =SUM(F37:F46) -> 4961.2626 | G47: =SUM(G37:G46) -> 9533.2626 | H47: =SUM(H37:H46) -> 4961.2626 | I47: =SUM(I37:I46) -> 4961.2626 | J47: =SUM(J37:J46) -> 9533.2626 | K47: =SUM(K37:K46) -> 4961.2626 | L47: =SUM(L37:L46) -> 4961.2626 | ... O47: =SUM(O37:O46) -> 4961.2626 | P47: =SUM(P38:P46) -> 88110.151
B48: 2. VALOR DE INSUMOS | C48: =SUM(P49:P52) -> 18889.98
B49: Insecticida | C49: =C25 -> 115 | D49: =C49*C35 -> 438.15 | G49: =C49*C35 -> 438.15 | J49: =D49 -> 438.15 | M49: =D49 -> 438.15 | P49: =D49*4 -> 1752.6
B50: Fungicida | C50: =C26 -> 92.5 | D50: =C50*C35 -> 352.425 | G50: =D50 -> 352.425 | J50: =D50 -> 352.425 | M50: =D50 -> 352.425 | P50: =D50*4 -> 1409.7
B51: Coadyuvantes | C51: =C27 -> 72 | D51: =C51*C35 -> 274.32 | G51: =D51 -> 274.32 | J51: =D51 -> 274.32 | M51: =D51 -> 274.32 | P51: =D51*4 -> 1097.28
B52: Herbicida | C52: =C29 -> 960 | D52: =G52 -> 3657.6 | G52: =C52*C35 -> 3657.6 | J52: =G52 -> 3657.6 | M52: =G52 -> 3657.6 | P52: =SUM(D52:M52) -> 14630.4
D53: =SUM(D49:D52) -> 4722.495 | E53: =SUM(E49:E52) -> 0 | F53: =SUM(F49:F52) -> 0 | G53: =SUM(G49:G52) -> 4722.495 | H53: =SUM(H49:H52) -> 0 | I53: =SUM(I49:I52) -> 0 | J53: =SUM(J49:J52) -> 4722.495 | K53: =SUM(K49:K52) -> 0 | ... P53: =SUM(P49:P52) -> 18889.98
D54: =D47+D53 -> 24542.758 | E54: =E47+E53 -> 4961.2626 | F54: =F47+F53 -> 4961.2626 | G54: =G47+G53 -> 14255.758 | H54: =H47+H53 -> 4961.2626 | I54: =I47+I53 -> 4961.2626 | J54: =J47+J53 -> 14255.758 | K54: =K47+K53 -> 4961.2626 | ... P54: =P47+P53 -> 107000.13
B57: CRONOGRAMA DE ACTIVIDADES - RESOCA - SEGUNDO AÑO
C58: 3.81 | D58: MES
B59: CONCEPTO | C59: COSTO HA | D59: 1 | E59: 2 | F59: 3 | G59: 4 | H59: 5 | I59: 6 | J59: 7 | K59: 8 | L59: 9 | M59: 10 | N59: 11 | O59: 12 | P59: TOTAL
B60: 3. LABORES CULTURALES | C60: =P70 -> 88110.151
B61: Desmonte o limpieza del terreno | C61: 1000 | D61: =C61*C8 -> 3810 | P61: =D61 -> 3810
B62: Rastreo y barbecho | C62: 1700 | D62: =C62*C8 -> 6477 | P62: =D62 -> 6477
B63: Aplicación de coadyuvantes | C63: 300 | D63: =C63*C8 -> 1143 | G63: =D63 -> 1143 | J63: =D63 -> 1143 | M63: =D63 -> 1143 | P63: =SUM(D63:M63) -> 4572
B64: Aplicación de insecticidas | C64: 300 | D64: =C64*C8 -> 1143 | G64: =D64 -> 1143 | J64: =D64 -> 1143 | M64: =D64 -> 1143 | P64: =SUM(D64:M64) -> 4572
B65: Aplicación de fungicidas | C65: 300 | D65: =C65*C8 -> 1143 | G65: =D65 -> 1143 | J65: =D65 -> 1143 | M65: =D65 -> 1143 | P65: =SUM(D65:M65) -> 4572
B66: Aplicación de herbicidas | C66: 300 | D66: =C66*C8 -> 1143 | G66: =D66 -> 1143 | J66: =D66 -> 1143 | M66: =D66 -> 1143 | P66: =SUM(D66:M66) -> 4572
B67: Sueldo Jefe departamento de cultivo | C67: 614.17323 | D67: =C67*C8 -> 2340 | E67: =D67 -> 2340 | F67: =D67 -> 2340 | G67: =D67 -> 2340 | H67: =D67 -> 2340 | I67: =D67 -> 2340 | J67: =D67 -> 2340 | K67: =D67 -> 2340 | L67: =D67 -> 2340 | M67: =D67 -> 2340 | N67: =D67 -> 2340 | O67: =D67 -> 2340 | P67: =SUM(D67:O67) -> 28080
B68: Sueldo jornalero de cultivo | C68: 511.81102 | D68: =C68*C8 -> 1950 | E68: =D68 -> 1950 | F68: =D68 -> 1950 | G68: =D68 -> 1950 | H68: =D68 -> 1950 | I68: =D68 -> 1950 | J68: =D68 -> 1950 | K68: =D68 -> 1950 | L68: =D68 -> 1950 | M68: =D68 -> 1950 | N68: =D68 -> 1950 | O68: =D68 -> 1950 | P68: =SUM(D68:O68) -> 23400
B69: Impuesto sobre nómina | D69: =D46 -> 671.2626 | E69: =D69 -> 671.2626 | F69: =D69 -> 671.2626 | G69: =D69 -> 671.2626 | H69: =D69 -> 671.2626 | I69: =D69 -> 671.2626 | J69: =D69 -> 671.2626 | K69: =D69 -> 671.2626 | L69: =D69 -> 671.2626 | M69: =D69 -> 671.2626 | N69: =D69 -> 671.2626 | O69: =D69 -> 671.2626 | P69: =SUM(D69:O69) -> 8055.1512
D70: =SUM(D61:D69) -> 19820.263 | E70: =SUM(E61:E69) -> 4961.2626 | F70: =SUM(F61:F69) -> 4961.2626 | G70: =SUM(G61:G69) -> 9533.2626 | H70: =SUM(H61:H69) -> 4961.2626 | I70: =SUM(I61:I69) -> 4961.2626 | J70: =SUM(J61:J69) -> 9533.2626 | K70: =SUM(K61:K69) -> 4961.2626 | ... P70: =SUM(P61:P69) -> 88110.151
B71: 4. VALOR DE INSUMOS | C71: =P76 -> 18889.98
B72: Insecticida | C72: 115 | D72: =C72*C8 -> 438.15 | G72: =D72 -> 438.15 | J72: =D72 -> 438.15 | M72: =D72 -> 438.15 | P72: =D72+G72+J72+M72 -> 1752.6
B73: Fungicida | C73: 92.5 | D73: =C73*C8 -> 352.425 | G73: =D73 -> 352.425 | J73: =D73 -> 352.425 | M73: =D73 -> 352.425 | P73: =D73+G73+J73+M73 -> 1409.7
B74: Coadyuvantes | C74: 72 | D74: =C74*C8 -> 274.32 | G74: =D74 -> 274.32 | J74: =D74 -> 274.32 | M74: =D74 -> 274.32 | P74: =D74+G74+J74+M74 -> 1097.28
B75: Herbicida | C75: 960 | D75: =C75*C8 -> 3657.6 | G75: =D75 -> 3657.6 | J75: =D75 -> 3657.6 | M75: =D75 -> 3657.6 | P75: =D75+G75+J75+M75 -> 14630.4
D76: =SUM(D72:D75) -> 4722.495 | E76: =SUM(E72:E75) -> 0 | F76: =SUM(F72:F75) -> 0 | G76: =SUM(G72:G75) -> 4722.495 | H76: =SUM(H72:H75) -> 0 | I76: =SUM(I72:I75) -> 0 | J76: =SUM(J72:J75) -> 4722.495 | K76: =SUM(K72:K75) -> 0 | ... P76: =SUM(P72:P75) -> 18889.98
C77: TOTAL | D77: =SUM(D70+D76) -> 24542.758 | E77: =SUM(E70+E76) -> 4961.2626 | F77: =SUM(F70+F76) -> 4961.2626 | G77: =SUM(G70+G76) -> 14255.758 | H77: =SUM(H70+H76) -> 4961.2626 | I77: =SUM(I70+I76) -> 4961.2626 | J77: =SUM(J70+J76) -> 14255.758 | K77: =SUM(K70+K76) -> 4961.2626 | ... O77: =SUM(O70+O76) -> 4961.2626 | P77: =P70+P76 -> 107000.13 | R77: =P77+125666.24 -> 232666.37
B81: CRONOGRAMA DE ACTIVIDADES SEGUNDO AÑO
B83: CONCEPTO | C83: 1 | D83: 2 | E83: 3 | F83: 4 | G83: 5 | H83: 6 | I83: 7 | J83: 8 | K83: 9 | L83: 10 | M83: 11 | N83: 12
B98: CRONOGRAMA DE ACTIVIDADES TERCER AÑO
B100: CONCEPTO | C100: 1 | D100: 2 | E100: 3 | F100: 4 | G100: 5 | H100: 6 | I100: 7 | J100: 8 | K100: 9 | L100: 10 | M100: 11 | N100: 12
B115: CRONOGRAMA DE ACTIVIDADES CUARTO AÑO
B117: CONCEPTO | C117: 1 | D117: 2 | E117: 3 | F117: 4 | G117: 5 | H117: 6 | I117: 7 | J117: 8 | K117: 9 | L117: 10 | M117: 11 | N117: 12
B133: Se siembra en ambos terrenos a la vez

Sheet CÁLCULO NÓMINA
A2: PROYECTO: | B2: Implementación de semilla CP57-536 | G2: ANOTACIÓN | H2: Se siembra en ambos terrenos a la vez
A3: SOCIEDAD | B3: Caña de la Loma
A4: BENEFICIARIOS:
A6: AÑO 1
A7: CÁLCULO DE NÓMINA (MENSUAL)
A9: Nombre del trabajador | B9: Área | C9: Puesto | D9: Actividades | E9: Tipo de contrato | F9: Días trabajados al mes (promedio) | G9: Pago diario | H9: Sueldo bruto | I9: ISR retenido | J9: IMSS | K9: ISN (patrón) | L9: Sueldo neto | N9: TOTAL ANUAL
A10: Raúl Antonio Don Juan Melchor | B10: Cultivo | C10: Jefe de departamento del cultivo | D10: Coordinar las labores agrícolas | E10: Por tiempo determinado | F10: 8 | G10: 300 | H10: =F10*G10 -> 2400 | I10: Exento | J10: =H10*0.025 -> 60 | K10: =H10*0.03 -> 72 | L10: =H10-J10 -> 2340 | N10: =L10*12 -> 28080
A11: Víctor Rosales Martínez | B11: Cultivo | C11: Fumigador | D11: Aplicación de agroquímicos | E11: Por tiempo determinado | F11: 5 | G11: 312.616 | H11: =F11*G11 -> 1563.08 | I11: Exento | J11: =H11*0.025 -> 39.077 | K11: =H11*0.03 -> 46.8924 | L11: =H11-J11 -> 1524.003 | N11: =L11*12 -> 18288.036 | P11: Nota: Aunque las actividades se realizan de manera trimestral, el cálculo de la nómina se estimó de forma mensual con fines de estandarización y practicidad en el análisis.
A12: Juan Rosales Pavón | B12: Cultivo | C12: Jornalero de cultivo | D12: Mantenimiento del terreno | E12: Por tiempo determinado | F12: 8 | G12: 250 | H12: =F12*G12 -> 2000 | I12: Exento | J12: =H12*0.025 -> 50 | K12: =H12*0.03 -> 60 | L12: =H12-J12 -> 1950 | N12: =L12*12 -> 23400
K13: =SUM(K10:K12) -> 178.8924 | L13: =SUM(L10:L12) -> 5814.003 | N13: =SUM(N10:O12) -> 69768.036
A16: Excepción de los productores asociados
A18: Nombre del trabajador | B18: Área | C18: Puesto | D18: Actividades | E18: Tipo de contrato | F18: Días trabajados al mes (promedio) | G18: Pago diario | H18: Sueldo bruto | I18: ISR retenido | J18: IMSS | K18: ISN | L18: Sueldo neto
A19: Andrés Rosas González | B19: Administración | C19: Socio cañero | D19: Supervisar las labores agrícolas | E19: Productor asociado (proveedor del ingenio) | F19: N/A | G19: N/A | H19: N/A | I19: N/A | J19: N/A | K19: N/A | L19: N/A | M19: Observación: No forma parte de la nómina. Figuran como patrones y proveedores del ingenio azucarero conforme a la LDSCA. Responsables del pago de jornaleros y cumplimiento fiscal ante IMSS e ISN.
A20: Beatriz Guadalupe Buelna González | B20: Administración | C20: Socio cañero | D20: Supervisar las labores agrícolas | E20: Productor asociado (proveedor del ingenio) | F20: N/A | G20: N/A | H20: N/A | I20: N/A | J20: N/A | K20: N/A | L20: N/A
A23: Excepción de los prestadores de servicios profesionales (MENSUAL)
A24: FIJOS
A25: Nombre del trabajador | B25: Área | C25: Puesto | D25: Actividades | E25: Tipo de contrato | F25: Honorario base (sin IVA) | G25: IVA trasladado (16%) | H25: Subtotal (facturado) | I25: Pago neto | K25: TOTAL ANUAL
A26: Andrea Rosas Buelna | B26: Administración | C26: Administradora | D26: Planificar y coordinar recursos humanos, materiales y financieros | E26: Honorarios profesionales (Régimen 612) | F26: 2000 | G26: =F26*0.16 -> 320 | H26: =F26+G26 -> 2320 | I26: =H26 -> 2320 | K26: =I26*12 -> 27840
A27: Gabriela Rosas Buelna | B27: Finanzas | C27: Contadora | D27: Registrar y controlar las operaciones financieras | E27: Honorarios profesionales (Régimen 612) | F27: 2500 | G27: =F27*0.16 -> 400 | H27: =F27+G27 -> 2900 | I27: =H27 -> 2900 | K27: =I27*12 -> 34800
I28: =SUM(I26:I27) -> 5220 | K28: =SUM(K26:L27) -> 62640
A31: Excepción del jornalero de siembra (MENSUAL)
A33: Nombre del trabajador | B33: Área | C33: Puesto | D33: Actividades | E33: Tipo de contrato | F33: Periodo laboral | G33: Pago diario | H33: Sueldo bruto | I33: ISR retenido | J33: IMSS | K33: ISN (patrón) | L33: Sueldo neto
A34: Juan Rosales Pavón | B34: Siembra | C34: Jornalero | D34: Labores de soca | E34: Por obra o proyecto (eventual agrícola) | F34: 12 días (etapa de siembra) | G34: 1367.695 | H34: =G34*12 -> 16412.34 | I34: Exento (LISR art. 93 fracc. XXVII, ingreso agrícola eventual) | J34: =H34*0.025 -> 410.3085 | K34: =H34*0.03 -> 492.3702 | L34: =H34-J34 -> 16002.032 | M34: Observación: Trabajador eventual agrícola contratado exclusivamente para la etapa de siembra (12 días). Se liquida al término del periodo conforme al art. 283 de la LFT y Modalidad 14 del IMSS. Exento de ISR por ingresos agrícolas.
K35: =SUM(K34:K34) -> 492.3702 | L35: =SUM(L34:L34) -> 16002.032
J37: TOTAL MENSUAL | L37: =L13+I28+L35 -> 27036.035 | O37: TOTAL ANUAL | Q37: =N13+K28+L35 -> 148410.07
A39: AÑO 2
A40: CÁLCULO DE NÓMINA
A42: Nombre del trabajador | B42: Área | C42: Puesto | D42: Actividades | E42: Tipo de contrato | F42: Días trabajados al mes (promedio) | G42: Pago diario | H42: Sueldo bruto | I42: ISR retenido | J42: IMSS | K42: ISN (patrón) | L42: Sueldo neto
A43: Raúl Antonio Don Juan Melchor | B43: Cultivo | C43: Jefe de departamento del cultivo | D43: Coordinar las labores agrícolas | E43: Por tiempo determinado | F43: 8 | G43: =300*1.12 -> 336 | H43: =F43*G43 -> 2688 | I43: Exento | J43: =H43*0.025 -> 67.2 | K43: =H43*0.03 -> 80.64 | L43: =H43-J43 -> 2620.8
A44: Víctor Rosales Martínez | B44: Cultivo | C44: Fumigador | D44: Aplicación de agroquímicos | E44: Por tiempo determinado | F44: 5 | G44: =312.616*1.12 -> 350.12992 | H44: =F44*G44 -> 1750.6496 | I44: Exento | J44: =H44*0.025 -> 43.76624 | K44: =H44*0.03 -> 52.519488 | L44: =H44-J44 -> 1706.8834
A45: Juan Rosales Pavón | B45: Cultivo | C45: Jornalero de cultivo | D45: Mantenimiento del terreno | E45: Por tiempo determinado | F45: 8 | G45: =250*1.12 -> 280 | H45: =F45*G45 -> 2240 | I45: Exento | J45: =H45*0.025 -> 56 | K45: =H45*0.03 -> 67.2 | L45: =H45-J45 -> 2184
K46: =SUM(K43:K45) -> 200.35949 | L46: =SUM(L43:L45) -> 6511.6834
A48: Excepción de los prestadores de servicios profesionales
A50: Nombre del trabajador | B50: Área | C50: Puesto | D50: Actividades | E50: Tipo de contrato | F50: Honorario base (sin IVA) | G50: IVA trasladado (16%) | H50: Subtotal (facturado) | I50: Pago neto
A51: Andrea Rosas Buelna | B51: Administración | C51: Administradora | D51: Planificar y coordinar recursos humanos, materiales y financieros | E51: Honorarios profesionales (Régimen 612) | F51: =2000*1.12 -> 2240 | G51: =F51*0.16 -> 358.4 | H51: =F51+G51 -> 2598.4 | I51: =H51 -> 2598.4
A52: Gabriela Rosas Buelna | B52: Finanzas | C52: Contadora | D52: Registrar y controlar las operaciones financieras | E52: Honorarios profesionales (Régimen 612) | F52: =2500*1.12 -> 2800 | G52: =F52*0.16 -> 448 | H52: =F52+G52 -> 3248 | I52: =H52 -> 3248
I53: =SUM(I51:I52) -> 5846.4
A55: Excepción del jornalero de siembra
A57: Nombre del trabajador | B57: Área | C57: Puesto | D57: Actividades | E57: Tipo de contrato | F57: Periodo laboral | G57: Pago diario | H57: Sueldo bruto | I57: ISR retenido | J57: IMSS | K57: ISN (patrón) | L57: Sueldo neto
A58: Juan Rosales Pavón | B58: Siembra | C58: Jornalero | D58: Labores de soca | E58: Por obra o proyecto (eventual agrícola) | F58: 12 días (etapa de siembra) | G58: =1367.695*1.12 -> 1531.8184 | H58: =G58*12 -> 18381.821 | I58: Exento (LISR art. 93 fracc. XXVII, ingreso agrícola eventual) | J58: =H58*0.025 -> 459.54552 | K58: =H58*0.03 -> 551.45462 | L58: =H58-J58 -> 17922.275
K59: =SUM(K58:K58) -> 551.45462 | L59: =SUM(L58:L58) -> 17922.275
J61: TOTAL | L61: =L46+I53+L59 -> 30280.359
A63: AÑO 3
A64: CÁLCULO DE NÓMINA
A66: Nombre del trabajador | B66: Área | C66: Puesto | D66: Actividades | E66: Tipo de contrato | F66: Días trabajados al mes (promedio) | G66: Pago diario | H66: Sueldo bruto | I66: ISR retenido | J66: IMSS | K66: ISN (patrón) | L66: Sueldo neto
A67: Raúl Antonio Don Juan Melchor | B67: Cultivo | C67: Jefe de departamento del cultivo | D67: Coordinar las labores agrícolas | E67: Por tiempo determinado | F67: 8 | G67: =300*1.12*1.12 -> 376.32 | H67: =F67*G67 -> 3010.56 | I67: Exento | J67: =H67*0.025 -> 75.264 | K67: =H67*0.03 -> 90.3168 | L67: =H67-J67 -> 2935.296
A68: Víctor Rosales Martínez | B68: Cultivo | C68: Fumigador | D68: Aplicación de agroquímicos | E68: Por tiempo determinado | F68: 5 | G68: =312.616*1.12*1.12 -> 392.14551 | H68: =F68*G68 -> 1960.7276 | I68: Exento | J68: =H68*0.025 -> 49.018189 | K68: =H68*0.03 -> 58.821827 | L68: =H68-J68 -> 1911.7094
A69: Juan Rosales Pavón | B69: Cultivo | C69: Jornalero de cultivo | D69: Mantenimiento del terreno | E69: Por tiempo determinado | F69: 8 | G69: =250*1.12*1.12 -> 313.6 | H69: =F69*G69 -> 2508.8 | I69: Exento | J69: =H69*0.025 -> 62.72 | K69: =H69*0.03 -> 75.264 | L69: =H69-J69 -> 2446.08
K70: =SUM(K67:K69) -> 224.40263 | L70: =SUM(L67:L69) -> 7293.0854
A72: Excepción de los prestadores de servicios profesionales
A74: Nombre del trabajador | B74: Área | C74: Puesto | D74: Actividades | E74: Tipo de contrato | F74: Honorario base (sin IVA) | G74: IVA trasladado (16%) | H74: Subtotal (facturado) | I74: Pago neto
A75: Andrea Rosas Buelna | B75: Administración | C75: Administradora | D75: Planificar y coordinar recursos humanos, materiales y financieros | E75: Honorarios profesionales (Régimen 612) | F75: =2000*1.12*1.12 -> 2508.8 | G75: =F75*0.16 -> 401.408 | H75: =F75+G75 -> 2910.208 | I75: =H75 -> 2910.208
A76: Gabriela Rosas Buelna | B76: Finanzas | C76: Contadora | D76: Registrar y controlar las operaciones financieras | E76: Honorarios profesionales (Régimen 612) | F76: =2500*1.12*1.12 -> 3136 | G76: =F76*0.16 -> 501.76 | H76: =F76+G76 -> 3637.76 | I76: =H76 -> 3637.76
I77: =SUM(I75:I76) -> 6547.968
A79: Excepción del jornalero de siembra
A81: Nombre del trabajador | B81: Área | C81: Puesto | D81: Actividades | E81: Tipo de contrato | F81: Periodo laboral | G81: Pago diario | H81: Sueldo bruto | I81: ISR retenido | J81: IMSS | K81: ISN (patrón) | L81: Sueldo neto
A82: Juan Rosales Pavón | B82: Siembra | C82: Jornalero | D82: Labores de soca | E82: Por obra o proyecto (eventual agrícola) | F82: 12 días (etapa de siembra) | G82: =1367.695*1.12*1.12 -> 1715.6366 | H82: =G82*12 -> 20587.639 | I82: Exento (LISR art. 93 fracc. XXVII, ingreso agrícola eventual) | J82: =H82*0.025 -> 514.69098 | K82: =H82*0.03 -> 617.62918 | L82: =H82-J82 -> 20072.948
K83: =SUM(K82:K82) -> 617.62918 | L83: =SUM(L82:L82) -> 20072.948
J85: TOTAL | L85: =L70+I77+L83 -> 33914.002
A87: AÑO 4
A88: CÁLCULO DE NÓMINA
A90: Nombre del trabajador | B90: Área | C90: Puesto | D90: Actividades | E90: Tipo de contrato | F90: Días trabajados al mes (promedio) | G90: Pago diario | H90: Sueldo bruto | I90: ISR retenido | J90: IMSS | K90: ISN (patrón) | L90: Sueldo neto
A91: Raúl Antonio Don Juan Melchor | B91: Cultivo | C91: Jefe de departamento del cultivo | D91: Coordinar las labores agrícolas | E91: Por tiempo determinado | F91: 8 | G91: =300*1.12*1.12*1.12 -> 421.4784 | H91: =F91*G91 -> 3371.8272 | I91: Exento | J91: =H91*0.025 -> 84.29568 | K91: =H91*0.03 -> 101.15482 | L91: =H91-J91 -> 3287.5315
A92: Víctor Rosales Martínez | B92: Cultivo | C92: Fumigador | D92: Aplicación de agroquímicos | E92: Por tiempo determinado | F92: 5 | G92: =312.616*1.12*1.12*1.12 -> 439.20297 | H92: =F92*G92 -> 2196.0149 | I92: Exento | J92: =H92*0.025 -> 54.900371 | K92: =H92*0.03 -> 65.880446 | L92: =H92-J92 -> 2141.1145
A93: Juan Rosales Pavón | B93: Cultivo | C93: Jornalero de cultivo | D93: Mantenimiento del terreno | E93: Por tiempo determinado | F93: 8 | G93: =250*1.12*1.12*1.12 -> 351.232 | H93: =F93*G93 -> 2809.856 | I93: Exento | J93: =H93*0.025 -> 70.2464 | K93: =H93*0.03 -> 84.29568 | L93: =H93-J93 -> 2739.6096
K94: =SUM(K91:K93) -> 251.33094 | L94: =SUM(L91:L93) -> 8168.2556
A96: Excepción de los prestadores de servicios profesionales
A98: Nombre del trabajador | B98: Área | C98: Puesto | D98: Actividades | E98: Tipo de contrato | F98: Honorario base (sin IVA) | G98: IVA trasladado (16%) | H98: Subtotal (facturado) | I98: Pago neto
A99: Andrea Rosas Buelna | B99: Administración | C99: Administradora | D99: Planificar y coordinar recursos humanos, materiales y financieros | E99: Honorarios profesionales (Régimen 612) | F99: =2000*1.12*1.12*1.12 -> 2809.856 | G99: =F99*0.16 -> 449.57696 | H99: =F99+G99 -> 3259.433 | I99: =H99 -> 3259.433
A100: Gabriela Rosas Buelna | B100: Finanzas | C100: Contadora | D100: Registrar y controlar las operaciones financieras | E100: Honorarios profesionales (Régimen 612) | F100: =2500*1.12*1.12*1.12 -> 3512.32 | G100: =F100*0.16 -> 561.9712 | H100: =F100+G100 -> 4074.2912 | I100: =H100 -> 4074.2912
I101: =SUM(I99:I100) -> 7333.7242
A103: Excepción del jornalero de siembra
A105: Nombre del trabajador | B105: Área | C105: Puesto | D105: Actividades | E105: Tipo de contrato | F105: Periodo laboral | G105: Pago diario | H105: Sueldo bruto | I105: ISR retenido | J105: IMSS | K105: ISN (patrón) | L105: Sueldo neto
A106: Juan Rosales Pavón | B106: Siembra | C106: Jornalero | D106: Labores de soca | E106: Por obra o proyecto (eventual agrícola) | F106: 12 días (etapa de siembra) | G106: =1367.695*1.12*1.12*1.12 -> 1921.513 | H106: =G106*12 -> 23058.156 | I106: Exento (LISR art. 93 fracc. XXVII, ingreso agrícola eventual) | J106: =H106*0.025 -> 576.4539 | K106: =H106*0.03 -> 691.74468 | L106: =H106-J106 -> 22481.702
K107: =SUM(K106:K106) -> 691.74468 | L107: =SUM(L106:L106) -> 22481.702
J109: TOTAL | L109: =L94+I101+L107 -> 37983.682
A111: AÑO 5
A112: CÁLCULO DE NÓMINA
A114: Nombre del trabajador | B114: Área | C114: Puesto | D114: Actividades | E114: Tipo de contrato | F114: Días trabajados al mes (promedio) | G114: Pago diario | H114: Sueldo bruto | I114: ISR retenido | J114: IMSS | K114: ISN (patrón) | L114: Sueldo neto
A115: Raúl Antonio Don Juan Melchor | B115: Cultivo | C115: Jefe de departamento del cultivo | D115: Coordinar las labores agrícolas | E115: Por tiempo determinado | F115: 8 | G115: =300*1.12*1.12*1.12*1.12 -> 472.05581 | H115: =F115*G115 -> 3776.4465 | I115: Exento | J115: =H115*0.025 -> 94.411162 | K115: =H115*0.03 -> 113.29339 | L115: =H115-J115 -> 3682.0353
A116: Víctor Rosales Martínez | B116: Cultivo | C116: Fumigador | D116: Aplicación de agroquímicos | E116: Por tiempo determinado | F116: 5 | G116: =312.616*1.12*1.12*1.12*1.12 -> 491.90733 | H116: =F116*G116 -> 2459.5366 | I116: Exento | J116: =H116*0.025 -> 61.488416 | K116: =H116*0.03 -> 73.786099 | L116: =H116-J116 -> 2398.0482
A117: Juan Rosales Pavón | B117: Cultivo | C117: Jornalero de cultivo | D117: Mantenimiento del terreno | E117: Por tiempo determinado | F117: 8 | G117: =250*1.12*1.12*1.12*1.12 -> 393.37984 | H117: =F117*G117 -> 3147.0387 | I117: Exento | J117: =H117*0.025 -> 78.675968 | K117: =H117*0.03 -> 94.411162 | L117: =H117-J117 -> 3068.3628
K118: =SUM(K115:K117) -> 281.49065 | L118: =SUM(L115:L117) -> 9148.4463
A120: Excepción de los prestadores de servicios profesionales
A122: Nombre del trabajador | B122: Área | C122: Puesto | D122: Actividades | E122: Tipo de contrato | F122: Honorario base (sin IVA) | G122: IVA trasladado (16%) | H122: Subtotal (facturado) | I122: Pago neto
A123: Andrea Rosas Buelna | B123: Administración | C123: Administradora | D123: Planificar y coordinar recursos humanos, materiales y financieros | E123: Honorarios profesionales (Régimen 612) | F123: =2000*1.12*1.12*1.12*1.12 -> 3147.0387 | G123: =F123*0.16 -> 503.5262 | H123: =F123+G123 -> 3650.5649 | I123: =H123 -> 3650.5649
A124: Gabriela Rosas Buelna | B124: Finanzas | C124: Contadora | D124: Registrar y controlar las operaciones financieras | E124: Honorarios profesionales (Régimen 612) | F124: =2500*1.12*1.12*1.12*1.12 -> 3933.7984 | G124: =F124*0.16 -> 629.40774 | H124: =F124+G124 -> 4563.2061 | I124: =H124 -> 4563.2061
I125: =SUM(I123:I124) -> 8213.7711
A127: Excepción del jornalero de siembra
A129: Nombre del trabajador | B129: Área | C129: Puesto | D129: Actividades | E129: Tipo de contrato | F129: Periodo laboral | G129: Pago diario | H129: Sueldo bruto | I129: ISR retenido | J129: IMSS | K129: ISN (patrón) | L129: Sueldo neto
A130: Juan Rosales Pavón | B130: Siembra | C130: Jornalero | D130: Labores de soca | E130: Por obra o proyecto (eventual agrícola) | F130: 12 días (etapa de siembra) | G130: =1367.695*1.12*1.12*1.12*1.12 -> 2152.0946 | H130: =G130*12 -> 25825.135 | I130: Exento (LISR art. 93 fracc. XXVII, ingreso agrícola eventual) | J130: =H130*0.025 -> 645.62837 | K130: =H130*0.03 -> 774.75404 | L130: =H130-J130 -> 25179.506
K131: =SUM(K130:K130) -> 774.75404 | L131: =SUM(L130:L130) -> 25179.506
J133: TOTAL | L133: =L118+I125+L131 -> 42541.724

Sheet DEFLACTACIÓN
D3: Valor a precios constantes 2024= | G3: (valor a precios corrientes 2024/deflactor a precios 2013)*100
A4: 2024 | B4: 1041.5
D5: Valor a precios constantes 2024= | G5: =B4 -> 1041.5 | H5: *100 | I5: =(G5/G6)*100 -> 1035.4993 | J5: Monto Real presupuestado para 2025 | N5: 1041.5 | O5: =N6-N5 -> -6
G6: 100.5795 | N6: 1035.5 | O6: =O5/N5 -> -0.0057609217
A7: Precio caña de azucar 2025-2026 | N7: 100 | O7: =O6*N7 -> -0.57609217 | P7: 0.0058
A9: 2025 | B9: =I5 -> 1035.4993 | D9: Valor a precios constantes 2025= | G9: =B9 -> 1035.4993 | H9: *100 | I9: =(G9/G10)*100 -> 1029.5331 | J9: Monto Real presupuestado para 2026 | N9: 1035.5 | O9: =N10-N9 -> -5.97
G10: =G6 -> 100.5795 | N10: 1029.53 | O10: =O9/N9 -> -0.0057653308
N11: 100 | O11: =O10*N11 -> -0.57653308 | P11: 0.0058
N14: 1029.53 | O14: =N15-N14 -> -5.93
A15: 2026 | B15: =I9 -> 1029.5331 | D15: Valor a precios constantes 2026= | G15: =B15 -> 1029.5331 | H15: *100 | I15: =(G15/G16)*100 -> 1023.6014 | J15: Monto Real presupuestado para 2027 | N15: 1023.6 | O15: =O14/N15 -> -0.0057932786
G16: =G6 -> 100.5795
N17: 100 | O17: =O15*N17 -> -0.57932786 | P17: 0.0058
A19: Precio caña de azucar 2027-2028 | N19: 1029.53 | O19: =N20-N19 -> -11.826226
A20: 2027 | B20: =I15 -> 1023.6014 | D20: Valor a precios constantes 2027 | G20: =B20 -> 1023.6014 | N20: =I21 -> 1017.7038 | O20: =O19/N20 -> -0.011620499
G21: =G16 -> 100.5795 | H21: 100 | I21: =(G20/G21)*H21 -> 1017.7038
N22: 100 | O22: =O20*N22 -> -1.1620499 | P22: 0.0058
A24: 2028 | B24: =I21 -> 1017.7038 | D24: Valor a precios constantes 2028 | G24: =B24 -> 1017.7038 | H24: 100 | I24: =(G24/G25)*H24 -> 1011.8402 | J24: Monto Real presupuestado para 2028
G25: =G16 -> 100.5795
A27: Precio caña de azucar 2029-2030
A29: 2029 | B29: =I24 -> 1011.8402 | D29: Valor a precios constantes 2029 | G29: =B29 -> 1011.8402 | H29: 100 | I29: =(G29/G30)*H29 -> 1006.0103 | J29: Monto Real presupuestado para 2029
G30: =G25 -> 100.5795
A32: 2030 | B32: =I29 -> 1006.0103 | D32: Valor a precios constantes 2030 | G32: =B32 -> 1006.0103 | H32: 100 | I32: =(G32/G34)*100 -> 1000.2091 | J32: Monto Real presupuestado para 2030
A34: Precio caña de azucar 2031-2032 | G34: 100.58
A36: 2031 | B36: =I32 -> 1000.2091 | D36: Valor a precios constantes 2031 | G36: =B36 -> 1000.2091 | H36: 100 | I36: =(G36/G37)*H36 -> 994.44136 | J36: Monto Real presupuestado para 2031
G37: 100.58
A39: 2032 | B39: =I36 -> 994.44136 | D39: Valor a precios constantes 2032 | G39: =B39 -> 994.44136 | H39: 100 | I39: =(G39/G40)*100 -> 988.70686 | J39: Monto Real presupuestado para 2032
G40: 100.58
